{"objects": {"bd7b70d9-44eb-4840-904c-192ede8f6052_features": {"type": "GeometryCollection", "geometries": [{"type": "Point", "properties": {"PLATE_ID": 106, "NAME": "202090344"}, "coordinates": [5421, 7879]}, {"type": "Point", "properties": {"PLATE_ID": 128, "NAME": "200920293"}, "coordinates": [3319, 7944]}, {"type": "Point", "properties": {"PLATE_ID": 291, "NAME": "202190090"}, "coordinates": [3979, 2351]}, {"type": "Point", "properties": {"PLATE_ID": 101, "NAME": "201510242"}, "coordinates": [4226, 5674]}, {"type": "Point", "properties": {"PLATE_ID": 101, "NAME": "201230260"}, "coordinates": [4039, 6404]}, {"type": "Point", "properties": {"PLATE_ID": 128, "NAME": "200910293"}, "coordinates": [3315, 7951]}, {"type": "Point", "properties": {"PLATE_ID": 106, "NAME": "202320345"}, "coordinates": [5494, 7868]}, {"type": "Point", "properties": {"PLATE_ID": 604, "NAME": "206010243"}, "coordinates": [8279, 5090]}, {"type": "Point", "properties": {"PLATE_ID": 604, "NAME": "206010261"}, "coordinates": [8467, 5437]}, {"type": "Point", "properties": {"PLATE_ID": 401, "NAME": "206010305"}, "coordinates": [7359, 8888]}, {"type": "Point", "properties": {"PLATE_ID": 401, "NAME": "206030306"}, "coordinates": [7303, 8927]}, {"type": "Point", "properties": {"PLATE_ID": 680, "NAME": "206060158"}, "coordinates": [7909, 2344]}, {"type": "Point", "properties": {"PLATE_ID": 628, "NAME": "206060274"}, "coordinates": [8950, 6545]}, {"type": "Point", "properties": {"PLATE_ID": 680, "NAME": "206070159"}, "coordinates": [7936, 2349]}, {"type": "Point", "properties": {"PLATE_ID": 604, "NAME": "206070262"}, "coordinates": [8521, 5369]}, {"type": "Point", "properties": {"PLATE_ID": 801, "NAME": "206080143"}, "coordinates": [7757, 1965]}, {"type": "Point", "properties": {"PLATE_ID": 680, "NAME": "206080160"}, "coordinates": [7967, 2355]}, {"type": "Point", "properties": {"PLATE_ID": 801, "NAME": "206090157"}, "coordinates": [7939, 2266]}, {"type": "Point", "properties": {"PLATE_ID": 680, "NAME": "206090160"}, "coordinates": [7979, 2347]}, {"type": "Point", "properties": {"PLATE_ID": 680, "NAME": "206090161"}, "coordinates": [7991, 2358]}, {"type": "Point", "properties": {"PLATE_ID": 801, "NAME": "206100138"}, "coordinates": [7696, 1815]}, {"type": "Point", "properties": {"PLATE_ID": 801, "NAME": "206100141"}, "coordinates": [7764, 1890]}, {"type": "Point", "properties": {"PLATE_ID": 401, "NAME": "206100325"}, "coordinates": [6519, 8949]}, {"type": "Point", "properties": {"PLATE_ID": 801, "NAME": "206110141"}, "coordinates": [7773, 1874]}, {"type": "Point", "properties": {"PLATE_ID": 604, "NAME": "206110263"}, "coordinates": [8562, 5324]}, {"type": "Point", "properties": {"PLATE_ID": 680, "NAME": "206120162"}, "coordinates": [8062, 2344]}, {"type": "Point", "properties": {"PLATE_ID": 604, "NAME": "206120259"}, "coordinates": [8527, 5236]}, {"type": "Point", "properties": {"PLATE_ID": 801, "NAME": "206090143"}, "coordinates": [7767, 1948]}, {"type": "Point", "properties": {"PLATE_ID": 801, "NAME": "206090144"}, "coordinates": [7782, 1964]}, {"type": "Point", "properties": {"PLATE_ID": 604, "NAME": "206130263"}, "coordinates": [8574, 5311]}, {"type": "Point", "properties": {"PLATE_ID": 401, "NAME": "206140323"}, "coordinates": [6560, 9000]}, {"type": "Point", "properties": {"PLATE_ID": 401, "NAME": "206150319"}, "coordinates": [6752, 9048]}, {"type": "Point", "properties": {"PLATE_ID": 604, "NAME": "206160253"}, "coordinates": [8503, 5051]}, {"type": "Point", "properties": {"PLATE_ID": 628, "NAME": "206160266"}, "coordinates": [8990, 6259]}, {"type": "Point", "properties": {"PLATE_ID": 628, "NAME": "206160274"}, "coordinates": [9038, 6441]}, {"type": "Point", "properties": {"PLATE_ID": 401, "NAME": "206160314"}, "coordinates": [6985, 9078]}, {"type": "Point", "properties": {"PLATE_ID": 401, "NAME": "206160316"}, "coordinates": [6890, 9070]}, {"type": "Point", "properties": {"PLATE_ID": 401, "NAME": "206160320"}, "coordinates": [6691, 9042]}, {"type": "Point", "properties": {"PLATE_ID": 604, "NAME": "206130258"}, "coordinates": [8534, 5201]}, {"type": "Point", "properties": {"PLATE_ID": 401, "NAME": "206180314"}, "coordinates": [6970, 9099]}, {"type": "Point", "properties": {"PLATE_ID": 801, "NAME": "206190151"}, "coordinates": [8064, 1993]}, {"type": "Point", "properties": {"PLATE_ID": 801, "NAME": "206190152"}, "coordinates": [8079, 2002]}, {"type": "Point", "properties": {"PLATE_ID": 801, "NAME": "206190153"}, "coordinates": [8095, 2020]}, {"type": "Point", "properties": {"PLATE_ID": 604, "NAME": "206190265"}, "coordinates": [8641, 5261]}, {"type": "Point", "properties": {"PLATE_ID": 628, "NAME": "206190269"}, "coordinates": [9032, 6295]}, {"type": "Point", "properties": {"PLATE_ID": 401, "NAME": "206190313"}, "coordinates": [7002, 9112]}, {"type": "Point", "properties": {"PLATE_ID": 401, "NAME": "206190322"}, "coordinates": [6596, 9059]}, {"type": "Point", "properties": {"PLATE_ID": 604, "NAME": "206200265"}, "coordinates": [8649, 5246]}, {"type": "Point", "properties": {"PLATE_ID": 628, "NAME": "206170275"}, "coordinates": [9062, 6465]}, {"type": "Point", "properties": {"PLATE_ID": 801, "NAME": "206180151"}, "coordinates": [8055, 1992]}, {"type": "Point", "properties": {"PLATE_ID": 401, "NAME": "206180313"}, "coordinates": [7028, 9108]}, {"type": "Point", "properties": {"PLATE_ID": 610, "NAME": "206210245"}, "coordinates": [8568, 5043]}, {"type": "Point", "properties": {"PLATE_ID": 610, "NAME": "206220245"}, "coordinates": [8582, 5033]}, {"type": "Point", "properties": {"PLATE_ID": 628, "NAME": "206240266"}, "coordinates": [9068, 6179]}, {"type": "Point", "properties": {"PLATE_ID": 628, "NAME": "206240267"}, "coordinates": [9071, 6197]}, {"type": "Point", "properties": {"PLATE_ID": 628, "NAME": "206240276"}, "coordinates": [9139, 6421]}, {"type": "Point", "properties": {"PLATE_ID": 401, "NAME": "206240310"}, "coordinates": [7172, 9179]}, {"type": "Point", "properties": {"PLATE_ID": 610, "NAME": "206250249"}, "coordinates": [8639, 5096]}, {"type": "Point", "properties": {"PLATE_ID": 628, "NAME": "206250265"}, "coordinates": [9074, 6144]}, {"type": "Point", "properties": {"PLATE_ID": 628, "NAME": "206250267"}, "coordinates": [9081, 6192]}, {"type": "Point", "properties": {"PLATE_ID": 401, "NAME": "206200308"}, "coordinates": [7247, 9139]}, {"type": "Point", "properties": {"PLATE_ID": 401, "NAME": "206200310"}, "coordinates": [7175, 9132]}, {"type": "Point", "properties": {"PLATE_ID": 401, "NAME": "206200318"}, "coordinates": [6749, 9099]}, {"type": "Point", "properties": {"PLATE_ID": 628, "NAME": "206260266"}, "coordinates": [9085, 6155]}, {"type": "Point", "properties": {"PLATE_ID": 401, "NAME": "206260308"}, "coordinates": [7273, 9207]}, {"type": "Point", "properties": {"PLATE_ID": 610, "NAME": "206270249"}, "coordinates": [8662, 5066]}, {"type": "Point", "properties": {"PLATE_ID": 628, "NAME": "206270269"}, "coordinates": [9118, 6230]}, {"type": "Point", "properties": {"PLATE_ID": 628, "NAME": "206270270"}, "coordinates": [9121, 6245]}, {"type": "Point", "properties": {"PLATE_ID": 610, "NAME": "206280250"}, "coordinates": [8678, 5067]}, {"type": "Point", "properties": {"PLATE_ID": 628, "NAME": "206280277"}, "coordinates": [9182, 6419]}, {"type": "Point", "properties": {"PLATE_ID": 401, "NAME": "206280308"}, "coordinates": [7278, 9230]}, {"type": "Point", "properties": {"PLATE_ID": 610, "NAME": "206290249"}, "coordinates": [8681, 5040]}, {"type": "Point", "properties": {"PLATE_ID": 610, "NAME": "206290250"}, "coordinates": [8689, 5064]}, {"type": "Point", "properties": {"PLATE_ID": 628, "NAME": "206250269"}, "coordinates": [9097, 6240]}, {"type": "Point", "properties": {"PLATE_ID": 610, "NAME": "206260247"}, "coordinates": [8633, 5019]}, {"type": "Point", "properties": {"PLATE_ID": 628, "NAME": "206260265"}, "coordinates": [9078, 6145]}, {"type": "Point", "properties": {"PLATE_ID": 610, "NAME": "206300250"}, "coordinates": [8700, 5058]}, {"type": "Point", "properties": {"PLATE_ID": 401, "NAME": "206300308"}, "coordinates": [7263, 9259]}, {"type": "Point", "properties": {"PLATE_ID": 610, "NAME": "206320250"}, "coordinates": [8721, 5028]}, {"type": "Point", "properties": {"PLATE_ID": 610, "NAME": "206330250"}, "coordinates": [8730, 5023]}, {"type": "Point", "properties": {"PLATE_ID": 610, "NAME": "206330251"}, "coordinates": [8735, 5037]}, {"type": "Point", "properties": {"PLATE_ID": 401, "NAME": "206330306"}, "coordinates": [7345, 9298]}, {"type": "Point", "properties": {"PLATE_ID": 401, "NAME": "206330307"}, "coordinates": [7330, 9298]}, {"type": "Point", "properties": {"PLATE_ID": 401, "NAME": "206360304"}, "coordinates": [7515, 9334]}, {"type": "Point", "properties": {"PLATE_ID": 610, "NAME": "206380251"}, "coordinates": [8784, 4983]}, {"type": "Point", "properties": {"PLATE_ID": 610, "NAME": "206380254"}, "coordinates": [8804, 5052]}, {"type": "Point", "properties": {"PLATE_ID": 610, "NAME": "206290251"}, "coordinates": [8692, 5081]}, {"type": "Point", "properties": {"PLATE_ID": 610, "NAME": "206420254"}, "coordinates": [8840, 5018]}, {"type": "Point", "properties": {"PLATE_ID": 610, "NAME": "206420257"}, "coordinates": [8867, 5082]}, {"type": "Point", "properties": {"PLATE_ID": 610, "NAME": "206430257"}, "coordinates": [8873, 5088]}, {"type": "Point", "properties": {"PLATE_ID": 610, "NAME": "206430258"}, "coordinates": [8877, 5094]}, {"type": "Point", "properties": {"PLATE_ID": 401, "NAME": "206500302"}, "coordinates": [7648, 9521]}, {"type": "Point", "properties": {"PLATE_ID": 401, "NAME": "206520306"}, "coordinates": [7311, 9533]}, {"type": "Point", "properties": {"PLATE_ID": 801, "NAME": "206540096"}, "coordinates": [7330, 258]}, {"type": "Point", "properties": {"PLATE_ID": 801, "NAME": "206540130"}, "coordinates": [8764, 1084]}, {"type": "Point", "properties": {"PLATE_ID": 401, "NAME": "206540301"}, "coordinates": [7735, 9577]}, {"type": "Point", "properties": {"PLATE_ID": 401, "NAME": "206380305"}, "coordinates": [7458, 9359]}, {"type": "Point", "properties": {"PLATE_ID": 610, "NAME": "206410254"}, "coordinates": [8837, 5013]}, {"type": "Point", "properties": {"PLATE_ID": 801, "NAME": "206560094"}, "coordinates": [7254, 203]}, {"type": "Point", "properties": {"PLATE_ID": 801, "NAME": "206560130"}, "coordinates": [8835, 1066]}, {"type": "Point", "properties": {"PLATE_ID": 801, "NAME": "206560132"}, "coordinates": [8830, 1115]}, {"type": "Point", "properties": {"PLATE_ID": 801, "NAME": "206560134"}, "coordinates": [8848, 1171]}, {"type": "Point", "properties": {"PLATE_ID": 801, "NAME": "206560136"}, "coordinates": [8868, 1231]}, {"type": "Point", "properties": {"PLATE_ID": 801, "NAME": "206570132"}, "coordinates": [8879, 1121]}, {"type": "Point", "properties": {"PLATE_ID": 801, "NAME": "206570133"}, "coordinates": [8888, 1150]}, {"type": "Point", "properties": {"PLATE_ID": 401, "NAME": "206570302"}, "coordinates": [7630, 9617]}, {"type": "Point", "properties": {"PLATE_ID": 401, "NAME": "206570303"}, "coordinates": [7591, 9621]}, {"type": "Point", "properties": {"PLATE_ID": 401, "NAME": "206540302"}, "coordinates": [7678, 9577]}, {"type": "Point", "properties": {"PLATE_ID": 801, "NAME": "206550093"}, "coordinates": [7088, 201]}, {"type": "Point", "properties": {"PLATE_ID": 401, "NAME": "206550302"}, "coordinates": [7629, 9596]}, {"type": "Point", "properties": {"PLATE_ID": 801, "NAME": "206590115"}, "coordinates": [8787, 645]}, {"type": "Point", "properties": {"PLATE_ID": 401, "NAME": "206590303"}, "coordinates": [7545, 9637]}, {"type": "Point", "properties": {"PLATE_ID": 801, "NAME": "206600109"}, "coordinates": [8759, 471]}, {"type": "Point", "properties": {"PLATE_ID": 801, "NAME": "206600118"}, "coordinates": [8895, 717]}, {"type": "Point", "properties": {"PLATE_ID": 801, "NAME": "206600130"}, "coordinates": [8976, 1053]}, {"type": "Point", "properties": {"PLATE_ID": 801, "NAME": "206600132"}, "coordinates": [8983, 1103]}, {"type": "Point", "properties": {"PLATE_ID": 801, "NAME": "206610111"}, "coordinates": [8854, 517]}, {"type": "Point", "properties": {"PLATE_ID": 801, "NAME": "206620114"}, "coordinates": [8959, 603]}, {"type": "Point", "properties": {"PLATE_ID": 801, "NAME": "206630113"}, "coordinates": [8994, 586]}, {"type": "Point", "properties": {"PLATE_ID": 801, "NAME": "206580134"}, "coordinates": [8917, 1165]}, {"type": "Point", "properties": {"PLATE_ID": 401, "NAME": "206580302"}, "coordinates": [7639, 9625]}, {"type": "Point", "properties": {"PLATE_ID": 801, "NAME": "206590113"}, "coordinates": [8765, 589]}, {"type": "Point", "properties": {"PLATE_ID": 405, "NAME": "206680306"}, "coordinates": [1416, 9999]}, {"type": "Point", "properties": {"PLATE_ID": 405, "NAME": "206740308"}, "coordinates": [1819, 9892]}, {"type": "Point", "properties": {"PLATE_ID": 405, "NAME": "206780305"}, "coordinates": [584, 9868]}, {"type": "Point", "properties": {"PLATE_ID": 405, "NAME": "206790305"}, "coordinates": [743, 9860]}, {"type": "Point", "properties": {"PLATE_ID": 405, "NAME": "206830306"}, "coordinates": [987, 9806]}, {"type": "Point", "properties": {"PLATE_ID": 802, "NAME": "206840012"}, "coordinates": [5700, 746]}, {"type": "Point", "properties": {"PLATE_ID": 802, "NAME": "206860010"}, "coordinates": [5619, 778]}, {"type": "Point", "properties": {"PLATE_ID": 834, "NAME": "206910136"}, "coordinates": [9419, 1147]}, {"type": "Point", "properties": {"PLATE_ID": 834, "NAME": "206920136"}, "coordinates": [9440, 1135]}, {"type": "Point", "properties": {"PLATE_ID": 801, "NAME": "206630114"}, "coordinates": [8991, 600]}, {"type": "Point", "properties": {"PLATE_ID": 401, "NAME": "206650304"}, "coordinates": [7364, 9712]}, {"type": "Point", "properties": {"PLATE_ID": 807, "NAME": "206960090"}, "coordinates": [1398, 274]}, {"type": "Point", "properties": {"PLATE_ID": 807, "NAME": "206960091"}, "coordinates": [1413, 291]}, {"type": "Point", "properties": {"PLATE_ID": 807, "NAME": "206970087"}, "coordinates": [1531, 202]}, {"type": "Point", "properties": {"PLATE_ID": 807, "NAME": "206970089"}, "coordinates": [1500, 248]}, {"type": "Point", "properties": {"PLATE_ID": 807, "NAME": "206980087"}, "coordinates": [1647, 198]}, {"type": "Point", "properties": {"PLATE_ID": 807, "NAME": "206990088"}, "coordinates": [1818, 217]}, {"type": "Point", "properties": {"PLATE_ID": 807, "NAME": "207000092"}, "coordinates": [1789, 348]}, {"type": "Point", "properties": {"PLATE_ID": 806, "NAME": "207060097"}, "coordinates": [0, 0]}, {"type": "Point", "properties": {"PLATE_ID": 806, "NAME": "207060098"}, "coordinates": [9999, 23]}, {"type": "Point", "properties": {"PLATE_ID": 806, "NAME": "207070097"}, "coordinates": [337, 20]}, {"type": "Point", "properties": {"PLATE_ID": 807, "NAME": "206940090"}, "coordinates": [1172, 269]}, {"type": "Point", "properties": {"PLATE_ID": 807, "NAME": "206950088"}, "coordinates": [1340, 218]}, {"type": "Point", "properties": {"PLATE_ID": 807, "NAME": "206960088"}, "coordinates": [1405, 215]}, {"type": "Point", "properties": {"PLATE_ID": 806, "NAME": "207070098"}, "coordinates": [507, 41]}, {"type": "Point", "properties": {"PLATE_ID": 101, "NAME": "201330257"}, "coordinates": [4117, 6237]}, {"type": "Point", "properties": {"PLATE_ID": 102, "NAME": "203110323"}, "coordinates": [5701, 7178]}, {"type": "Point", "properties": {"PLATE_ID": 106, "NAME": "201930339"}, "coordinates": [5305, 7805]}, {"type": "Point", "properties": {"PLATE_ID": 707, "NAME": "203410241"}, "coordinates": [5240, 5769]}, {"type": "Point", "properties": {"PLATE_ID": 106, "NAME": "202160343"}, "coordinates": [5433, 7850]}, {"type": "Point", "properties": {"PLATE_ID": 315, "NAME": "203580286"}, "coordinates": [5684, 6465]}, {"type": "Point", "properties": {"PLATE_ID": 315, "NAME": "203570289"}, "coordinates": [5668, 6554]}, {"type": "Point", "properties": {"PLATE_ID": 106, "NAME": "201940339"}, "coordinates": [5319, 7816]}, {"type": "Point", "properties": {"PLATE_ID": 101, "NAME": "201980258"}, "coordinates": [4828, 5768]}, {"type": "Point", "properties": {"PLATE_ID": 101, "NAME": "201410274"}, "coordinates": [4315, 6578]}, {"type": "Point", "properties": {"PLATE_ID": 802, "NAME": "201330010"}, "coordinates": [4898, 852]}, {"type": "Point", "properties": {"PLATE_ID": 307, "NAME": "203870275"}, "coordinates": [6125, 5504]}, {"type": "Point", "properties": {"PLATE_ID": 309, "NAME": "203870336"}, "coordinates": [5706, 7886]}, {"type": "Point", "properties": {"PLATE_ID": 305, "NAME": "203810281"}, "coordinates": [5916, 6388]}, {"type": "Point", "properties": {"PLATE_ID": 106, "NAME": "202030345"}, "coordinates": [5428, 7929]}, {"type": "Point", "properties": {"PLATE_ID": 101, "NAME": "201240253"}, "coordinates": [3991, 6207]}, {"type": "Point", "properties": {"PLATE_ID": 101, "NAME": "201220287"}, "coordinates": [4246, 7059]}, {"type": "Point", "properties": {"PLATE_ID": 101, "NAME": "201570249"}, "coordinates": [4330, 5795]}, {"type": "Point", "properties": {"PLATE_ID": 106, "NAME": "202110346"}, "coordinates": [5451, 7923]}, {"type": "Point", "properties": {"PLATE_ID": 101, "NAME": "201910266"}, "coordinates": [4782, 6020]}, {"type": "Point", "properties": {"PLATE_ID": 307, "NAME": "203830272"}, "coordinates": [6073, 5540]}, {"type": "Point", "properties": {"PLATE_ID": 307, "NAME": "203860275"}, "coordinates": [6122, 5522]}, {"type": "Point", "properties": {"PLATE_ID": 315, "NAME": "203860288"}, "coordinates": [5940, 6597]}, {"type": "Point", "properties": {"PLATE_ID": 102, "NAME": "203180328"}, "coordinates": [5720, 7314]}, {"type": "Point", "properties": {"PLATE_ID": 130, "NAME": "201130260"}, "coordinates": [3886, 6387]}, {"type": "Point", "properties": {"PLATE_ID": 106, "NAME": "202170343"}, "coordinates": [5435, 7850]}, {"type": "Point", "properties": {"PLATE_ID": 307, "NAME": "203840272"}, "coordinates": [6077, 5521]}, {"type": "Point", "properties": {"PLATE_ID": 101, "NAME": "201660246"}, "coordinates": [4415, 5653]}, {"type": "Point", "properties": {"PLATE_ID": 101, "NAME": "201660252"}, "coordinates": [4444, 5803]}, {"type": "Point", "properties": {"PLATE_ID": 315, "NAME": "203570283"}, "coordinates": [5680, 6382]}, {"type": "Point", "properties": {"PLATE_ID": 102, "NAME": "203100322"}, "coordinates": [5697, 7150]}, {"type": "Point", "properties": {"PLATE_ID": 102, "NAME": "203140324"}, "coordinates": [5712, 7200]}, {"type": "Point", "properties": {"PLATE_ID": 315, "NAME": "203570286"}, "coordinates": [5675, 6462]}, {"type": "Point", "properties": {"PLATE_ID": 315, "NAME": "203810282"}, "coordinates": [5914, 6415]}, {"type": "Point", "properties": {"PLATE_ID": 106, "NAME": "202230345"}, "coordinates": [5472, 7882]}, {"type": "Point", "properties": {"PLATE_ID": 101, "NAME": "201480256"}, "coordinates": [4274, 6077]}, {"type": "Point", "properties": {"PLATE_ID": 302, "NAME": "204020291"}, "coordinates": [6070, 6747]}, {"type": "Point", "properties": {"PLATE_ID": 101, "NAME": "201840260"}, "coordinates": [4676, 5893]}, {"type": "Point", "properties": {"PLATE_ID": 101, "NAME": "201530241"}, "coordinates": [4244, 5625]}, {"type": "Point", "properties": {"PLATE_ID": 714, "NAME": "203750217"}, "coordinates": [5428, 4666]}, {"type": "Point", "properties": {"PLATE_ID": 129, "NAME": "201200267"}, "coordinates": [4002, 6509]}, {"type": "Point", "properties": {"PLATE_ID": 101, "NAME": "201380259"}, "coordinates": [4182, 6228]}, {"type": "Point", "properties": {"PLATE_ID": 101, "NAME": "201610245"}, "coordinates": [4357, 5662]}, {"type": "Point", "properties": {"PLATE_ID": 101, "NAME": "201380248"}, "coordinates": [4112, 5950]}, {"type": "Point", "properties": {"PLATE_ID": 315, "NAME": "203800282"}, "coordinates": [5904, 6407]}, {"type": "Point", "properties": {"PLATE_ID": 315, "NAME": "203800283"}, "coordinates": [5900, 6445]}, {"type": "Point", "properties": {"PLATE_ID": 305, "NAME": "203780280"}, "coordinates": [5888, 6351]}, {"type": "Point", "properties": {"PLATE_ID": 128, "NAME": "200970290"}, "coordinates": [3317, 7820]}, {"type": "Point", "properties": {"PLATE_ID": 315, "NAME": "203810283"}, "coordinates": [5907, 6445]}, {"type": "Point", "properties": {"PLATE_ID": 201, "NAME": "202580128"}, "coordinates": [4657, 3144]}, {"type": "Point", "properties": {"PLATE_ID": 307, "NAME": "203860273"}, "coordinates": [6093, 5496]}, {"type": "Point", "properties": {"PLATE_ID": 109, "NAME": "202060256"}, "coordinates": [4912, 5684]}, {"type": "Point", "properties": {"PLATE_ID": 315, "NAME": "203810284"}, "coordinates": [5907, 6466]}, {"type": "Point", "properties": {"PLATE_ID": 102, "NAME": "203130326"}, "coordinates": [5702, 7251]}, {"type": "Point", "properties": {"PLATE_ID": 102, "NAME": "203140323"}, "coordinates": [5716, 7171]}, {"type": "Point", "properties": {"PLATE_ID": 101, "NAME": "201500250"}, "coordinates": [4262, 5890]}, {"type": "Point", "properties": {"PLATE_ID": 803, "NAME": "202180031"}, "coordinates": [3925, 1232]}, {"type": "Point", "properties": {"PLATE_ID": 315, "NAME": "203570290"}, "coordinates": [5667, 6563]}, {"type": "Point", "properties": {"PLATE_ID": 804, "NAME": "201870025"}, "coordinates": [4281, 964]}, {"type": "Point", "properties": {"PLATE_ID": 101, "NAME": "201650253"}, "coordinates": [4439, 5843]}, {"type": "Point", "properties": {"PLATE_ID": 102, "NAME": "203200328"}, "coordinates": [5728, 7328]}, {"type": "Point", "properties": {"PLATE_ID": 101, "NAME": "201580251"}, "coordinates": [4353, 5844]}, {"type": "Point", "properties": {"PLATE_ID": 128, "NAME": "200960289"}, "coordinates": [3309, 7815]}, {"type": "Point", "properties": {"PLATE_ID": 106, "NAME": "202100346"}, "coordinates": [5446, 7919]}, {"type": "Point", "properties": {"PLATE_ID": 128, "NAME": "200960290"}, "coordinates": [3311, 7831]}, {"type": "Point", "properties": {"PLATE_ID": 128, "NAME": "200930290"}, "coordinates": [3287, 7864]}, {"type": "Point", "properties": {"PLATE_ID": 106, "NAME": "202160344"}, "coordinates": [5437, 7864]}, {"type": "Point", "properties": {"PLATE_ID": 101, "NAME": "201460246"}, "coordinates": [4194, 5818]}, {"type": "Point", "properties": {"PLATE_ID": 101, "NAME": "201610243"}, "coordinates": [4344, 5612]}, {"type": "Point", "properties": {"PLATE_ID": 101, "NAME": "201480257"}, "coordinates": [4277, 6103]}, {"type": "Point", "properties": {"PLATE_ID": 307, "NAME": "203790269"}, "coordinates": [6021, 5574]}, {"type": "Point", "properties": {"PLATE_ID": 102, "NAME": "203170328"}, "coordinates": [5714, 7302]}, {"type": "Point", "properties": {"PLATE_ID": 102, "NAME": "203110324"}, "coordinates": [5699, 7194]}, {"type": "Point", "properties": {"PLATE_ID": 101, "NAME": "201360252"}, "coordinates": [4115, 6067]}, {"type": "Point", "properties": {"PLATE_ID": 307, "NAME": "203840273"}, "coordinates": [6086, 5533]}, {"type": "Point", "properties": {"PLATE_ID": 128, "NAME": "200910295"}, "coordinates": [3342, 7989]}, {"type": "Point", "properties": {"PLATE_ID": 127, "NAME": "201320268"}, "coordinates": [4086, 6560]}, {"type": "Point", "properties": {"PLATE_ID": 102, "NAME": "203160328"}, "coordinates": [5712, 7303]}, {"type": "Point", "properties": {"PLATE_ID": 305, "NAME": "203790281"}, "coordinates": [5898, 6379]}, {"type": "Point", "properties": {"PLATE_ID": 315, "NAME": "203750279"}, "coordinates": [5865, 6310]}, {"type": "Point", "properties": {"PLATE_ID": 307, "NAME": "203880272"}, "coordinates": [6096, 5454]}, {"type": "Point", "properties": {"PLATE_ID": 201, "NAME": "202610123"}, "coordinates": [4681, 2990]}, {"type": "Point", "properties": {"PLATE_ID": 101, "NAME": "202000259"}, "coordinates": [4850, 5784]}, {"type": "Point", "properties": {"PLATE_ID": 101, "NAME": "201470275"}, "coordinates": [4386, 6557]}, {"type": "Point", "properties": {"PLATE_ID": 202, "NAME": "202510115"}, "coordinates": [4529, 2828]}, {"type": "Point", "properties": {"PLATE_ID": 102, "NAME": "203150326"}, "coordinates": [5711, 7266]}, {"type": "Point", "properties": {"PLATE_ID": 315, "NAME": "203770282"}, "coordinates": [5873, 6407]}, {"type": "Point", "properties": {"PLATE_ID": 101, "NAME": "201510243"}, "coordinates": [4232, 5696]}, {"type": "Point", "properties": {"PLATE_ID": 101, "NAME": "201460265"}, "coordinates": [4309, 6319]}, {"type": "Point", "properties": {"PLATE_ID": 101, "NAME": "201970258"}, "coordinates": [4813, 5775]}, {"type": "Point", "properties": {"PLATE_ID": 127, "NAME": "200980289"}, "coordinates": [3663, 7061]}, {"type": "Point", "properties": {"PLATE_ID": 307, "NAME": "203850273"}, "coordinates": [6092, 5508]}, {"type": "Point", "properties": {"PLATE_ID": 305, "NAME": "203850282"}, "coordinates": [5949, 6423]}, {"type": "Point", "properties": {"PLATE_ID": 315, "NAME": "203590286"}, "coordinates": [5694, 6475]}, {"type": "Point", "properties": {"PLATE_ID": 102, "NAME": "203190328"}, "coordinates": [5724, 7327]}, {"type": "Point", "properties": {"PLATE_ID": 0, "NAME": "200280317"}, "coordinates": [5069, 4991]}, {"type": "Point", "properties": {"PLATE_ID": 101, "NAME": "201990259"}, "coordinates": [4843, 5793]}, {"type": "Point", "properties": {"PLATE_ID": 0, "NAME": "203780260"}, "coordinates": [5331, 7243]}, {"type": "Point", "properties": {"PLATE_ID": 101, "NAME": "201480250"}, "coordinates": [4237, 5914]}, {"type": "Point", "properties": {"PLATE_ID": 123, "NAME": "200550306"}, "coordinates": [3984, 7865]}, {"type": "Point", "properties": {"PLATE_ID": 201, "NAME": "202640135"}, "coordinates": [4772, 3306]}, {"type": "Point", "properties": {"PLATE_ID": 201, "NAME": "202580127"}, "coordinates": [4650, 3120]}, {"type": "Point", "properties": {"PLATE_ID": 315, "NAME": "203540286"}, "coordinates": [5644, 6450]}, {"type": "Point", "properties": {"PLATE_ID": 101, "NAME": "201980259"}, "coordinates": [4832, 5799]}, {"type": "Point", "properties": {"PLATE_ID": 313, "NAME": "203460287"}, "coordinates": [5571, 6478]}, {"type": "Point", "properties": {"PLATE_ID": 305, "NAME": "203840281"}, "coordinates": [5943, 6405]}, {"type": "Point", "properties": {"PLATE_ID": 305, "NAME": "203780279"}, "coordinates": [5895, 6330]}, {"type": "Point", "properties": {"PLATE_ID": 309, "NAME": "203860336"}, "coordinates": [5700, 7883]}, {"type": "Point", "properties": {"PLATE_ID": 106, "NAME": "201620333"}, "coordinates": [5117, 7813]}, {"type": "Point", "properties": {"PLATE_ID": 101, "NAME": "200830315"}, "coordinates": [4332, 7988]}, {"type": "Point", "properties": {"PLATE_ID": 305, "NAME": "203790277"}, "coordinates": [5906, 6264]}, {"type": "Point", "properties": {"PLATE_ID": 104, "NAME": "201380237"}, "coordinates": [3988, 5979]}, {"type": "Point", "properties": {"PLATE_ID": 315, "NAME": "203820283"}, "coordinates": [5918, 6449]}, {"type": "Point", "properties": {"PLATE_ID": 302, "NAME": "204020292"}, "coordinates": [6069, 6772]}, {"type": "Point", "properties": {"PLATE_ID": 305, "NAME": "203800281"}, "coordinates": [5905, 6392]}, {"type": "Point", "properties": {"PLATE_ID": 309, "NAME": "203930337"}, "coordinates": [5725, 7920]}, {"type": "Point", "properties": {"PLATE_ID": 106, "NAME": "202160346"}, "coordinates": [5462, 7911]}, {"type": "Point", "properties": {"PLATE_ID": 305, "NAME": "203830281"}, "coordinates": [5934, 6391]}, {"type": "Point", "properties": {"PLATE_ID": 315, "NAME": "203830283"}, "coordinates": [5931, 6444]}, {"type": "Point", "properties": {"PLATE_ID": 101, "NAME": "201660242"}, "coordinates": [4398, 5552]}, {"type": "Point", "properties": {"PLATE_ID": 315, "NAME": "203750288"}, "coordinates": [5841, 6558]}, {"type": "Point", "properties": {"PLATE_ID": 101, "NAME": "201480248"}, "coordinates": [4219, 5852]}, {"type": "Point", "properties": {"PLATE_ID": 102, "NAME": "203160323"}, "coordinates": [5725, 7172]}, {"type": "Point", "properties": {"PLATE_ID": 102, "NAME": "203150323"}, "coordinates": [5721, 7167]}, {"type": "Point", "properties": {"PLATE_ID": 201, "NAME": "202580129"}, "coordinates": [4659, 3162]}, {"type": "Point", "properties": {"PLATE_ID": 101, "NAME": "201460251"}, "coordinates": [4217, 5955]}, {"type": "Point", "properties": {"PLATE_ID": 315, "NAME": "203570287"}, "coordinates": [5674, 6490]}, {"type": "Point", "properties": {"PLATE_ID": 106, "NAME": "201440332"}, "coordinates": [5033, 7886]}, {"type": "Point", "properties": {"PLATE_ID": 0, "NAME": "200630130"}, "coordinates": [873, 3600]}, {"type": "Point", "properties": {"PLATE_ID": 307, "NAME": "203830273"}, "coordinates": [6082, 5544]}, {"type": "Point", "properties": {"PLATE_ID": 102, "NAME": "203160329"}, "coordinates": [5708, 7328]}, {"type": "Point", "properties": {"PLATE_ID": 307, "NAME": "203870273"}, "coordinates": [6100, 5479]}, {"type": "Point", "properties": {"PLATE_ID": 102, "NAME": "203150327"}, "coordinates": [5711, 7275]}, {"type": "Point", "properties": {"PLATE_ID": 102, "NAME": "202960346"}, "coordinates": [5581, 7788]}, {"type": "Point", "properties": {"PLATE_ID": 315, "NAME": "203750284"}, "coordinates": [5853, 6451]}, {"type": "Point", "properties": {"PLATE_ID": 102, "NAME": "203170327"}, "coordinates": [5715, 7300]}, {"type": "Point", "properties": {"PLATE_ID": 102, "NAME": "203140326"}, "coordinates": [5706, 7258]}, {"type": "Point", "properties": {"PLATE_ID": 315, "NAME": "203790282"}, "coordinates": [5895, 6412]}, {"type": "Point", "properties": {"PLATE_ID": 612, "NAME": "205570238"}, "coordinates": [7367, 4076]}, {"type": "Point", "properties": {"PLATE_ID": 0, "NAME": "203650259"}, "coordinates": [5146, 7212]}, {"type": "Point", "properties": {"PLATE_ID": 106, "NAME": "201880336"}, "coordinates": [5257, 7770]}, {"type": "Point", "properties": {"PLATE_ID": 106, "NAME": "201880342"}, "coordinates": [5338, 7888]}, {"type": "Point", "properties": {"PLATE_ID": 714, "NAME": "203740217"}, "coordinates": [5426, 4689]}, {"type": "Point", "properties": {"PLATE_ID": 101, "NAME": "201300280"}, "coordinates": [4263, 6833]}, {"type": "Point", "properties": {"PLATE_ID": 102, "NAME": "203160327"}, "coordinates": [5713, 7299]}, {"type": "Point", "properties": {"PLATE_ID": 106, "NAME": "202120346"}, "coordinates": [5453, 7921]}, {"type": "Point", "properties": {"PLATE_ID": 101, "NAME": "201310261"}, "coordinates": [4129, 6344]}, {"type": "Point", "properties": {"PLATE_ID": 106, "NAME": "202370344"}, "coordinates": [5502, 7847]}, {"type": "Point", "properties": {"PLATE_ID": 307, "NAME": "203820269"}, "coordinates": [6024, 5519]}, {"type": "Point", "properties": {"PLATE_ID": 291, "NAME": "202410076"}, "coordinates": [4237, 1860]}, {"type": "Point", "properties": {"PLATE_ID": 101, "NAME": "201600247"}, "coordinates": [4355, 5726]}, {"type": "Point", "properties": {"PLATE_ID": 101, "NAME": "201540232"}, "coordinates": [4207, 5398]}, {"type": "Point", "properties": {"PLATE_ID": 101, "NAME": "201960258"}, "coordinates": [4806, 5779]}, {"type": "Point", "properties": {"PLATE_ID": 101, "NAME": "201620256"}, "coordinates": [4427, 5960]}, {"type": "Point", "properties": {"PLATE_ID": 407, "NAME": "205360267"}, "coordinates": [7655, 7437]}, {"type": "Point", "properties": {"PLATE_ID": 101, "NAME": "201980257"}, "coordinates": [4827, 5744]}, {"type": "Point", "properties": {"PLATE_ID": 701, "NAME": "204030115"}, "coordinates": [4490, 2202]}, {"type": "Point", "properties": {"PLATE_ID": 701, "NAME": "204030116"}, "coordinates": [4501, 2216]}, {"type": "Point", "properties": {"PLATE_ID": 307, "NAME": "203840266"}, "coordinates": [5996, 5449]}, {"type": "Point", "properties": {"PLATE_ID": 701, "NAME": "204260158"}, "coordinates": [5460, 2532]}, {"type": "Point", "properties": {"PLATE_ID": 701, "NAME": "204260159"}, "coordinates": [5464, 2549]}, {"type": "Point", "properties": {"PLATE_ID": 511, "NAME": "204260263"}, "coordinates": [6452, 6141]}, {"type": "Point", "properties": {"PLATE_ID": 508, "NAME": "204290241"}, "coordinates": [6156, 4500]}, {"type": "Point", "properties": {"PLATE_ID": 508, "NAME": "204290243"}, "coordinates": [6165, 4552]}, {"type": "Point", "properties": {"PLATE_ID": 701, "NAME": "204300159"}, "coordinates": [5534, 2483]}, {"type": "Point", "properties": {"PLATE_ID": 508, "NAME": "204300241"}, "coordinates": [6159, 4498]}, {"type": "Point", "properties": {"PLATE_ID": 508, "NAME": "204300242"}, "coordinates": [6170, 4516]}, {"type": "Point", "properties": {"PLATE_ID": 701, "NAME": "204350164"}, "coordinates": [5677, 2511]}, {"type": "Point", "properties": {"PLATE_ID": 302, "NAME": "204180322"}, "coordinates": [5985, 7613]}, {"type": "Point", "properties": {"PLATE_ID": 701, "NAME": "204190120"}, "coordinates": [4755, 1939]}, {"type": "Point", "properties": {"PLATE_ID": 302, "NAME": "204040291"}, "coordinates": [6088, 6767]}, {"type": "Point", "properties": {"PLATE_ID": 302, "NAME": "204040292"}, "coordinates": [6082, 6779]}, {"type": "Point", "properties": {"PLATE_ID": 701, "NAME": "204180122"}, "coordinates": [4788, 1999]}, {"type": "Point", "properties": {"PLATE_ID": 701, "NAME": "204180123"}, "coordinates": [4798, 2009]}, {"type": "Point", "properties": {"PLATE_ID": 701, "NAME": "204190122"}, "coordinates": [4789, 1967]}, {"type": "Point", "properties": {"PLATE_ID": 701, "NAME": "204200121"}, "coordinates": [4779, 1944]}, {"type": "Point", "properties": {"PLATE_ID": 701, "NAME": "204200122"}, "coordinates": [4792, 1955]}, {"type": "Point", "properties": {"PLATE_ID": 504, "NAME": "204200253"}, "coordinates": [6142, 4747]}, {"type": "Point", "properties": {"PLATE_ID": 701, "NAME": "204210122"}, "coordinates": [4815, 1940]}, {"type": "Point", "properties": {"PLATE_ID": 701, "NAME": "204230122"}, "coordinates": [4844, 1894]}, {"type": "Point", "properties": {"PLATE_ID": 701, "NAME": "204240123"}, "coordinates": [4878, 1888]}, {"type": "Point", "properties": {"PLATE_ID": 701, "NAME": "204240155"}, "coordinates": [5388, 2505]}, {"type": "Point", "properties": {"PLATE_ID": 302, "NAME": "204020290"}, "coordinates": [6074, 6716]}, {"type": "Point", "properties": {"PLATE_ID": 302, "NAME": "204070289"}, "coordinates": [6129, 6720]}, {"type": "Point", "properties": {"PLATE_ID": 302, "NAME": "204070292"}, "coordinates": [6113, 6781]}, {"type": "Point", "properties": {"PLATE_ID": 311, "NAME": "204070326"}, "coordinates": [5882, 7681]}, {"type": "Point", "properties": {"PLATE_ID": 309, "NAME": "203920333"}, "coordinates": [5749, 7831]}, {"type": "Point", "properties": {"PLATE_ID": 701, "NAME": "204150127"}, "coordinates": [4849, 2142]}, {"type": "Point", "properties": {"PLATE_ID": 701, "NAME": "204160143"}, "coordinates": [5121, 2411]}, {"type": "Point", "properties": {"PLATE_ID": 701, "NAME": "204170144"}, "coordinates": [5143, 2418]}, {"type": "Point", "properties": {"PLATE_ID": 302, "NAME": "204170322"}, "coordinates": [5979, 7619]}, {"type": "Point", "properties": {"PLATE_ID": 311, "NAME": "204060326"}, "coordinates": [5879, 7681]}, {"type": "Point", "properties": {"PLATE_ID": 701, "NAME": "204070115"}, "coordinates": [4535, 2113]}, {"type": "Point", "properties": {"PLATE_ID": 305, "NAME": "203920281"}, "coordinates": [6024, 6429]}, {"type": "Point", "properties": {"PLATE_ID": 302, "NAME": "203920287"}, "coordinates": [6001, 6582]}, {"type": "Point", "properties": {"PLATE_ID": 302, "NAME": "203910287"}, "coordinates": [5988, 6596]}, {"type": "Point", "properties": {"PLATE_ID": 305, "NAME": "203820281"}, "coordinates": [5928, 6394]}, {"type": "Point", "properties": {"PLATE_ID": 701, "NAME": "204070116"}, "coordinates": [4543, 2123]}, {"type": "Point", "properties": {"PLATE_ID": 307, "NAME": "204070255"}, "coordinates": [5986, 4883]}, {"type": "Point", "properties": {"PLATE_ID": 302, "NAME": "204070288"}, "coordinates": [6130, 6695]}, {"type": "Point", "properties": {"PLATE_ID": 305, "NAME": "204010281"}, "coordinates": [6107, 6474]}, {"type": "Point", "properties": {"PLATE_ID": 701, "NAME": "204020116"}, "coordinates": [4501, 2219]}, {"type": "Point", "properties": {"PLATE_ID": 701, "NAME": "203990113"}, "coordinates": [4413, 2253]}, {"type": "Point", "properties": {"PLATE_ID": 308, "NAME": "203990268"}, "coordinates": [6097, 5218]}, {"type": "Point", "properties": {"PLATE_ID": 311, "NAME": "203990339"}, "coordinates": [5730, 7990]}, {"type": "Point", "properties": {"PLATE_ID": 315, "NAME": "203550287"}, "coordinates": [5656, 6486]}, {"type": "Point", "properties": {"PLATE_ID": 315, "NAME": "203550286"}, "coordinates": [5657, 6464]}, {"type": "Point", "properties": {"PLATE_ID": 302, "NAME": "204050292"}, "coordinates": [6095, 6787]}, {"type": "Point", "properties": {"PLATE_ID": 307, "NAME": "204060254"}, "coordinates": [5967, 4873]}, {"type": "Point", "properties": {"PLATE_ID": 302, "NAME": "204040288"}, "coordinates": [6101, 6682]}, {"type": "Point", "properties": {"PLATE_ID": 302, "NAME": "204040290"}, "coordinates": [6096, 6728]}, {"type": "Point", "properties": {"PLATE_ID": 309, "NAME": "203900335"}, "coordinates": [5725, 7862]}, {"type": "Point", "properties": {"PLATE_ID": 315, "NAME": "203560289"}, "coordinates": [5665, 6542]}, {"type": "Point", "properties": {"PLATE_ID": 315, "NAME": "203560288"}, "coordinates": [5662, 6511]}, {"type": "Point", "properties": {"PLATE_ID": 315, "NAME": "203560287"}, "coordinates": [5667, 6495]}, {"type": "Point", "properties": {"PLATE_ID": 315, "NAME": "203550289"}, "coordinates": [5649, 6540]}, {"type": "Point", "properties": {"PLATE_ID": 309, "NAME": "203890335"}, "coordinates": [5721, 7867]}, {"type": "Point", "properties": {"PLATE_ID": 315, "NAME": "203900285"}, "coordinates": [5988, 6530]}, {"type": "Point", "properties": {"PLATE_ID": 315, "NAME": "203890284"}, "coordinates": [5986, 6491]}, {"type": "Point", "properties": {"PLATE_ID": 305, "NAME": "204000280"}, "coordinates": [6104, 6446]}, {"type": "Point", "properties": {"PLATE_ID": 0, "NAME": "204050254"}, "coordinates": [5709, 7064]}, {"type": "Point", "properties": {"PLATE_ID": 302, "NAME": "204050288"}, "coordinates": [6113, 6688]}, {"type": "Point", "properties": {"PLATE_ID": 302, "NAME": "204050290"}, "coordinates": [6104, 6733]}, {"type": "Point", "properties": {"PLATE_ID": 302, "NAME": "204050291"}, "coordinates": [6096, 6758]}, {"type": "Point", "properties": {"PLATE_ID": 102, "NAME": "203120324"}, "coordinates": [5701, 7189]}, {"type": "Point", "properties": {"PLATE_ID": 315, "NAME": "203730279"}, "coordinates": [5847, 6297]}, {"type": "Point", "properties": {"PLATE_ID": 308, "NAME": "203960272"}, "coordinates": [6127, 5310]}, {"type": "Point", "properties": {"PLATE_ID": 308, "NAME": "204000276"}, "coordinates": [6197, 5292]}, {"type": "Point", "properties": {"PLATE_ID": 315, "NAME": "203520289"}, "coordinates": [5628, 6529]}, {"type": "Point", "properties": {"PLATE_ID": 315, "NAME": "203540289"}, "coordinates": [5639, 6545]}, {"type": "Point", "properties": {"PLATE_ID": 302, "NAME": "204060288"}, "coordinates": [6122, 6692]}, {"type": "Point", "properties": {"PLATE_ID": 315, "NAME": "203530288"}, "coordinates": [5639, 6519]}, {"type": "Point", "properties": {"PLATE_ID": 313, "NAME": "203530295"}, "coordinates": [5626, 6704]}, {"type": "Point", "properties": {"PLATE_ID": 311, "NAME": "203940336"}, "coordinates": [5731, 7911]}, {"type": "Point", "properties": {"PLATE_ID": 308, "NAME": "203950272"}, "coordinates": [6125, 5321]}, {"type": "Point", "properties": {"PLATE_ID": 305, "NAME": "203820278"}, "coordinates": [5937, 6304]}, {"type": "Point", "properties": {"PLATE_ID": 604, "NAME": "205560255"}, "coordinates": [8085, 6114]}, {"type": "Point", "properties": {"PLATE_ID": 302, "NAME": "204060289"}, "coordinates": [6117, 6707]}, {"type": "Point", "properties": {"PLATE_ID": 315, "NAME": "203880288"}, "coordinates": [5957, 6592]}, {"type": "Point", "properties": {"PLATE_ID": 307, "NAME": "203890271"}, "coordinates": [6088, 5423]}, {"type": "Point", "properties": {"PLATE_ID": 302, "NAME": "204090289"}, "coordinates": [6150, 6722]}, {"type": "Point", "properties": {"PLATE_ID": 701, "NAME": "204100118"}, "coordinates": [4618, 2101]}, {"type": "Point", "properties": {"PLATE_ID": 701, "NAME": "204100119"}, "coordinates": [4633, 2095]}, {"type": "Point", "properties": {"PLATE_ID": 302, "NAME": "204100288"}, "coordinates": [6160, 6717]}, {"type": "Point", "properties": {"PLATE_ID": 305, "NAME": "203940283"}, "coordinates": [6032, 6493]}, {"type": "Point", "properties": {"PLATE_ID": 302, "NAME": "204050289"}, "coordinates": [6112, 6699]}, {"type": "Point", "properties": {"PLATE_ID": 302, "NAME": "203970286"}, "coordinates": [6046, 6593]}, {"type": "Point", "properties": {"PLATE_ID": 311, "NAME": "203970338"}, "coordinates": [5734, 7955]}, {"type": "Point", "properties": {"PLATE_ID": 302, "NAME": "204100289"}, "coordinates": [6155, 6723]}, {"type": "Point", "properties": {"PLATE_ID": 302, "NAME": "204110288"}, "coordinates": [6165, 6710]}, {"type": "Point", "properties": {"PLATE_ID": 701, "NAME": "204130121"}, "coordinates": [4712, 2078]}, {"type": "Point", "properties": {"PLATE_ID": 701, "NAME": "204140144"}, "coordinates": [5101, 2458]}, {"type": "Point", "properties": {"PLATE_ID": 302, "NAME": "203860289"}, "coordinates": [5938, 6616]}, {"type": "Point", "properties": {"PLATE_ID": 307, "NAME": "203820272"}, "coordinates": [6067, 5553]}, {"type": "Point", "properties": {"PLATE_ID": 307, "NAME": "203820273"}, "coordinates": [6078, 5557]}, {"type": "Point", "properties": {"PLATE_ID": 307, "NAME": "203820271"}, "coordinates": [6054, 5543]}, {"type": "Point", "properties": {"PLATE_ID": 302, "NAME": "204060291"}, "coordinates": [6106, 6772]}, {"type": "Point", "properties": {"PLATE_ID": 302, "NAME": "204060292"}, "coordinates": [6102, 6779]}, {"type": "Point", "properties": {"PLATE_ID": 307, "NAME": "203830271"}, "coordinates": [6058, 5530]}, {"type": "Point", "properties": {"PLATE_ID": 701, "NAME": "204090116"}, "coordinates": [4562, 2088]}, {"type": "Point", "properties": {"PLATE_ID": 308, "NAME": "204090257"}, "coordinates": [6017, 4879]}, {"type": "Point", "properties": {"PLATE_ID": 302, "NAME": "204090288"}, "coordinates": [6148, 6706]}, {"type": "Point", "properties": {"PLATE_ID": 701, "NAME": "203980117"}, "coordinates": [4475, 2325]}, {"type": "Point", "properties": {"PLATE_ID": 315, "NAME": "203570285"}, "coordinates": [5677, 6439]}, {"type": "Point", "properties": {"PLATE_ID": 701, "NAME": "204080115"}, "coordinates": [4544, 2098]}, {"type": "Point", "properties": {"PLATE_ID": 701, "NAME": "204080116"}, "coordinates": [4558, 2105]}, {"type": "Point", "properties": {"PLATE_ID": 302, "NAME": "204080288"}, "coordinates": [6145, 6695]}, {"type": "Point", "properties": {"PLATE_ID": 701, "NAME": "204050113"}, "coordinates": [4472, 2140]}, {"type": "Point", "properties": {"PLATE_ID": 701, "NAME": "204050116"}, "coordinates": [4529, 2183]}, {"type": "Point", "properties": {"PLATE_ID": 302, "NAME": "204030284"}, "coordinates": [6117, 6570]}, {"type": "Point", "properties": {"PLATE_ID": 309, "NAME": "203920334"}, "coordinates": [5744, 7839]}, {"type": "Point", "properties": {"PLATE_ID": 309, "NAME": "203930336"}, "coordinates": [5728, 7910]}, {"type": "Point", "properties": {"PLATE_ID": 307, "NAME": "203880271"}, "coordinates": [6081, 5443]}, {"type": "Point", "properties": {"PLATE_ID": 302, "NAME": "204030291"}, "coordinates": [6083, 6750]}, {"type": "Point", "properties": {"PLATE_ID": 302, "NAME": "204030292"}, "coordinates": [6076, 6780]}, {"type": "Point", "properties": {"PLATE_ID": 302, "NAME": "203960289"}, "coordinates": [6030, 6666]}, {"type": "Point", "properties": {"PLATE_ID": 308, "NAME": "203970274"}, "coordinates": [6161, 5327]}, {"type": "Point", "properties": {"PLATE_ID": 305, "NAME": "204000281"}, "coordinates": [6102, 6471]}, {"type": "Point", "properties": {"PLATE_ID": 311, "NAME": "204000339"}, "coordinates": [5733, 7990]}, {"type": "Point", "properties": {"PLATE_ID": 0, "NAME": "203860255"}, "coordinates": [5447, 7099]}, {"type": "Point", "properties": {"PLATE_ID": 302, "NAME": "204080289"}, "coordinates": [6137, 6717]}, {"type": "Point", "properties": {"PLATE_ID": 302, "NAME": "204080290"}, "coordinates": [6127, 6758]}, {"type": "Point", "properties": {"PLATE_ID": 701, "NAME": "204090115"}, "coordinates": [4545, 2083]}, {"type": "Point", "properties": {"PLATE_ID": 701, "NAME": "204040116"}, "coordinates": [4512, 2187]}, {"type": "Point", "properties": {"PLATE_ID": 701, "NAME": "204040117"}, "coordinates": [4540, 2199]}, {"type": "Point", "properties": {"PLATE_ID": 315, "NAME": "203730283"}, "coordinates": [5832, 6414]}, {"type": "Point", "properties": {"PLATE_ID": 123, "NAME": "200380299"}, "coordinates": [3752, 8002]}, {"type": "Point", "properties": {"PLATE_ID": 802, "NAME": "201320010"}, "coordinates": [4902, 851]}, {"type": "Point", "properties": {"PLATE_ID": 503, "NAME": "204490229"}, "coordinates": [6258, 3901]}, {"type": "Point", "properties": {"PLATE_ID": 512, "NAME": "204490259"}, "coordinates": [6646, 5293]}, {"type": "Point", "properties": {"PLATE_ID": 512, "NAME": "204510258"}, "coordinates": [6652, 5235]}, {"type": "Point", "properties": {"PLATE_ID": 302, "NAME": "204510300"}, "coordinates": [6421, 7257]}, {"type": "Point", "properties": {"PLATE_ID": 302, "NAME": "204510301"}, "coordinates": [6414, 7287]}, {"type": "Point", "properties": {"PLATE_ID": 302, "NAME": "204510309"}, "coordinates": [6327, 7489]}, {"type": "Point", "properties": {"PLATE_ID": 302, "NAME": "204520301"}, "coordinates": [6420, 7312]}, {"type": "Point", "properties": {"PLATE_ID": 302, "NAME": "204530270"}, "coordinates": [6680, 6540]}, {"type": "Point", "properties": {"PLATE_ID": 302, "NAME": "204530297"}, "coordinates": [6470, 7197]}, {"type": "Point", "properties": {"PLATE_ID": 302, "NAME": "204530301"}, "coordinates": [6429, 7303]}, {"type": "Point", "properties": {"PLATE_ID": 302, "NAME": "204530302"}, "coordinates": [6417, 7326]}, {"type": "Point", "properties": {"PLATE_ID": 302, "NAME": "204500301"}, "coordinates": [6410, 7279]}, {"type": "Point", "properties": {"PLATE_ID": 702, "NAME": "204510139"}, "coordinates": [5838, 2679]}, {"type": "Point", "properties": {"PLATE_ID": 512, "NAME": "204510257"}, "coordinates": [6652, 5232]}, {"type": "Point", "properties": {"PLATE_ID": 302, "NAME": "204560302"}, "coordinates": [6443, 7349]}, {"type": "Point", "properties": {"PLATE_ID": 702, "NAME": "204570152"}, "coordinates": [6090, 2840]}, {"type": "Point", "properties": {"PLATE_ID": 702, "NAME": "204570153"}, "coordinates": [6097, 2844]}, {"type": "Point", "properties": {"PLATE_ID": 302, "NAME": "204570290"}, "coordinates": [6567, 7062]}, {"type": "Point", "properties": {"PLATE_ID": 302, "NAME": "204570297"}, "coordinates": [6505, 7235]}, {"type": "Point", "properties": {"PLATE_ID": 302, "NAME": "204590297"}, "coordinates": [6519, 7251]}, {"type": "Point", "properties": {"PLATE_ID": 302, "NAME": "204600289"}, "coordinates": [6597, 7064]}, {"type": "Point", "properties": {"PLATE_ID": 302, "NAME": "204600298"}, "coordinates": [6513, 7289]}, {"type": "Point", "properties": {"PLATE_ID": 302, "NAME": "204600308"}, "coordinates": [6399, 7522]}, {"type": "Point", "properties": {"PLATE_ID": 302, "NAME": "204540295"}, "coordinates": [6490, 7165]}, {"type": "Point", "properties": {"PLATE_ID": 302, "NAME": "204560296"}, "coordinates": [6503, 7208]}, {"type": "Point", "properties": {"PLATE_ID": 512, "NAME": "204630251"}, "coordinates": [6764, 5007]}, {"type": "Point", "properties": {"PLATE_ID": 512, "NAME": "204630252"}, "coordinates": [6765, 5012]}, {"type": "Point", "properties": {"PLATE_ID": 512, "NAME": "204640243"}, "coordinates": [6754, 4770]}, {"type": "Point", "properties": {"PLATE_ID": 512, "NAME": "204640245"}, "coordinates": [6759, 4836]}, {"type": "Point", "properties": {"PLATE_ID": 512, "NAME": "204640252"}, "coordinates": [6783, 5016]}, {"type": "Point", "properties": {"PLATE_ID": 302, "NAME": "204640322"}, "coordinates": [6246, 7858]}, {"type": "Point", "properties": {"PLATE_ID": 302, "NAME": "204650285"}, "coordinates": [6683, 7024]}, {"type": "Point", "properties": {"PLATE_ID": 512, "NAME": "204660241"}, "coordinates": [6774, 4714]}, {"type": "Point", "properties": {"PLATE_ID": 302, "NAME": "204660286"}, "coordinates": [6681, 7044]}, {"type": "Point", "properties": {"PLATE_ID": 302, "NAME": "204610292"}, "coordinates": [6579, 7156]}, {"type": "Point", "properties": {"PLATE_ID": 503, "NAME": "204620241"}, "coordinates": [6492, 4081]}, {"type": "Point", "properties": {"PLATE_ID": 512, "NAME": "204620252"}, "coordinates": [6761, 5019]}, {"type": "Point", "properties": {"PLATE_ID": 302, "NAME": "204750309"}, "coordinates": [6499, 7650]}, {"type": "Point", "properties": {"PLATE_ID": 302, "NAME": "204760310"}, "coordinates": [6495, 7680]}, {"type": "Point", "properties": {"PLATE_ID": 503, "NAME": "204780224"}, "coordinates": [6607, 3482]}, {"type": "Point", "properties": {"PLATE_ID": 302, "NAME": "204780312"}, "coordinates": [6473, 7737]}, {"type": "Point", "properties": {"PLATE_ID": 503, "NAME": "204790224"}, "coordinates": [6615, 3484]}, {"type": "Point", "properties": {"PLATE_ID": 302, "NAME": "204800314"}, "coordinates": [6463, 7788]}, {"type": "Point", "properties": {"PLATE_ID": 302, "NAME": "204850317"}, "coordinates": [6447, 7884]}, {"type": "Point", "properties": {"PLATE_ID": 302, "NAME": "204890316"}, "coordinates": [6488, 7892]}, {"type": "Point", "properties": {"PLATE_ID": 506, "NAME": "204900246"}, "coordinates": [6631, 3257]}, {"type": "Point", "properties": {"PLATE_ID": 302, "NAME": "204660315"}, "coordinates": [6359, 7709]}, {"type": "Point", "properties": {"PLATE_ID": 302, "NAME": "204670303"}, "coordinates": [6507, 7459]}, {"type": "Point", "properties": {"PLATE_ID": 505, "NAME": "204680252"}, "coordinates": [6870, 4965]}, {"type": "Point", "properties": {"PLATE_ID": 302, "NAME": "204680284"}, "coordinates": [6718, 7030]}, {"type": "Point", "properties": {"PLATE_ID": 302, "NAME": "204680288"}, "coordinates": [6678, 7112]}, {"type": "Point", "properties": {"PLATE_ID": 505, "NAME": "204700253"}, "coordinates": [6890, 5000]}, {"type": "Point", "properties": {"PLATE_ID": 302, "NAME": "204700282"}, "coordinates": [6753, 6995]}, {"type": "Point", "properties": {"PLATE_ID": 302, "NAME": "204710330"}, "coordinates": [6156, 8048]}, {"type": "Point", "properties": {"PLATE_ID": 402, "NAME": "204720259"}, "coordinates": [7090, 6447]}, {"type": "Point", "properties": {"PLATE_ID": 302, "NAME": "204720283"}, "coordinates": [6764, 7038]}, {"type": "Point", "properties": {"PLATE_ID": 302, "NAME": "204720298"}, "coordinates": [6612, 7367]}, {"type": "Point", "properties": {"PLATE_ID": 505, "NAME": "204730247"}, "coordinates": [6928, 4838]}, {"type": "Point", "properties": {"PLATE_ID": 130, "NAME": "201140261"}, "coordinates": [3888, 6390]}, {"type": "Point", "properties": {"PLATE_ID": 106, "NAME": "202080345"}, "coordinates": [5432, 7905]}, {"type": "Point", "properties": {"PLATE_ID": 315, "NAME": "203660290"}, "coordinates": [5748, 6578]}, {"type": "Point", "properties": {"PLATE_ID": 307, "NAME": "203820267"}, "coordinates": [6000, 5495]}, {"type": "Point", "properties": {"PLATE_ID": 101, "NAME": "201860258"}, "coordinates": [4696, 5829]}, {"type": "Point", "properties": {"PLATE_ID": 315, "NAME": "203730281"}, "coordinates": [5837, 6355]}, {"type": "Point", "properties": {"PLATE_ID": 315, "NAME": "203730282"}, "coordinates": [5837, 6393]}, {"type": "Point", "properties": {"PLATE_ID": 201, "NAME": "202560133"}, "coordinates": [4644, 3282]}, {"type": "Point", "properties": {"PLATE_ID": 401, "NAME": "205710306"}, "coordinates": [7176, 8533]}, {"type": "Point", "properties": {"PLATE_ID": 611, "NAME": "205720226"}, "coordinates": [8052, 3891]}, {"type": "Point", "properties": {"PLATE_ID": 611, "NAME": "205720229"}, "coordinates": [8050, 3983]}, {"type": "Point", "properties": {"PLATE_ID": 611, "NAME": "205720230"}, "coordinates": [8043, 3994]}, {"type": "Point", "properties": {"PLATE_ID": 611, "NAME": "205720231"}, "coordinates": [8037, 4023]}, {"type": "Point", "properties": {"PLATE_ID": 611, "NAME": "205720232"}, "coordinates": [8040, 4059]}, {"type": "Point", "properties": {"PLATE_ID": 611, "NAME": "205720233"}, "coordinates": [8035, 4073]}, {"type": "Point", "properties": {"PLATE_ID": 611, "NAME": "205720234"}, "coordinates": [8036, 4101]}, {"type": "Point", "properties": {"PLATE_ID": 611, "NAME": "205720238"}, "coordinates": [8021, 4229]}, {"type": "Point", "properties": {"PLATE_ID": 611, "NAME": "205720239"}, "coordinates": [8020, 4251]}, {"type": "Point", "properties": {"PLATE_ID": 628, "NAME": "205710267"}, "coordinates": [8556, 6750]}, {"type": "Point", "properties": {"PLATE_ID": 604, "NAME": "205720256"}, "coordinates": [8202, 5823]}, {"type": "Point", "properties": {"PLATE_ID": 611, "NAME": "205730223"}, "coordinates": [8076, 3814]}, {"type": "Point", "properties": {"PLATE_ID": 611, "NAME": "205730228"}, "coordinates": [8060, 3947]}, {"type": "Point", "properties": {"PLATE_ID": 611, "NAME": "205730230"}, "coordinates": [8057, 4003]}, {"type": "Point", "properties": {"PLATE_ID": 611, "NAME": "205730231"}, "coordinates": [8051, 4021]}, {"type": "Point", "properties": {"PLATE_ID": 611, "NAME": "205730232"}, "coordinates": [8049, 4055]}, {"type": "Point", "properties": {"PLATE_ID": 611, "NAME": "205730233"}, "coordinates": [8047, 4079]}, {"type": "Point", "properties": {"PLATE_ID": 611, "NAME": "205730235"}, "coordinates": [8043, 4138]}, {"type": "Point", "properties": {"PLATE_ID": 611, "NAME": "205730236"}, "coordinates": [8040, 4165]}, {"type": "Point", "properties": {"PLATE_ID": 611, "NAME": "205730237"}, "coordinates": [8037, 4204]}, {"type": "Point", "properties": {"PLATE_ID": 611, "NAME": "205720244"}, "coordinates": [7998, 4369]}, {"type": "Point", "properties": {"PLATE_ID": 611, "NAME": "205730240"}, "coordinates": [8027, 4279]}, {"type": "Point", "properties": {"PLATE_ID": 611, "NAME": "205730243"}, "coordinates": [8010, 4365]}, {"type": "Point", "properties": {"PLATE_ID": 611, "NAME": "205730246"}, "coordinates": [8010, 4432]}, {"type": "Point", "properties": {"PLATE_ID": 604, "NAME": "205730251"}, "coordinates": [8147, 5730]}, {"type": "Point", "properties": {"PLATE_ID": 611, "NAME": "205740228"}, "coordinates": [8073, 3947]}, {"type": "Point", "properties": {"PLATE_ID": 611, "NAME": "205740229"}, "coordinates": [8071, 3974]}, {"type": "Point", "properties": {"PLATE_ID": 611, "NAME": "205740231"}, "coordinates": [8066, 4036]}, {"type": "Point", "properties": {"PLATE_ID": 611, "NAME": "205740232"}, "coordinates": [8063, 4062]}, {"type": "Point", "properties": {"PLATE_ID": 611, "NAME": "205740233"}, "coordinates": [8060, 4084]}, {"type": "Point", "properties": {"PLATE_ID": 611, "NAME": "205740234"}, "coordinates": [8054, 4117]}, {"type": "Point", "properties": {"PLATE_ID": 611, "NAME": "205730238"}, "coordinates": [8031, 4209]}, {"type": "Point", "properties": {"PLATE_ID": 611, "NAME": "205730239"}, "coordinates": [8023, 4253]}, {"type": "Point", "properties": {"PLATE_ID": 611, "NAME": "205740238"}, "coordinates": [8040, 4211]}, {"type": "Point", "properties": {"PLATE_ID": 611, "NAME": "205740244"}, "coordinates": [8024, 4386]}, {"type": "Point", "properties": {"PLATE_ID": 611, "NAME": "205750224"}, "coordinates": [8099, 3854]}, {"type": "Point", "properties": {"PLATE_ID": 611, "NAME": "205750225"}, "coordinates": [8106, 3869]}, {"type": "Point", "properties": {"PLATE_ID": 611, "NAME": "205750229"}, "coordinates": [8080, 3994]}, {"type": "Point", "properties": {"PLATE_ID": 611, "NAME": "205750230"}, "coordinates": [8080, 4007]}, {"type": "Point", "properties": {"PLATE_ID": 611, "NAME": "205750231"}, "coordinates": [8074, 4045]}, {"type": "Point", "properties": {"PLATE_ID": 611, "NAME": "205750232"}, "coordinates": [8074, 4071]}, {"type": "Point", "properties": {"PLATE_ID": 611, "NAME": "205750234"}, "coordinates": [8064, 4113]}, {"type": "Point", "properties": {"PLATE_ID": 611, "NAME": "205750237"}, "coordinates": [8062, 4199]}, {"type": "Point", "properties": {"PLATE_ID": 611, "NAME": "205740235"}, "coordinates": [8052, 4143]}, {"type": "Point", "properties": {"PLATE_ID": 611, "NAME": "205740237"}, "coordinates": [8052, 4196]}, {"type": "Point", "properties": {"PLATE_ID": 611, "NAME": "205750245"}, "coordinates": [8037, 4423]}, {"type": "Point", "properties": {"PLATE_ID": 611, "NAME": "205760226"}, "coordinates": [8106, 3898]}, {"type": "Point", "properties": {"PLATE_ID": 611, "NAME": "205760228"}, "coordinates": [8102, 3976]}, {"type": "Point", "properties": {"PLATE_ID": 611, "NAME": "205760229"}, "coordinates": [8100, 3987]}, {"type": "Point", "properties": {"PLATE_ID": 611, "NAME": "205760235"}, "coordinates": [8081, 4143]}, {"type": "Point", "properties": {"PLATE_ID": 611, "NAME": "205760236"}, "coordinates": [8074, 4174]}, {"type": "Point", "properties": {"PLATE_ID": 611, "NAME": "205760240"}, "coordinates": [8062, 4289]}, {"type": "Point", "properties": {"PLATE_ID": 611, "NAME": "205770218"}, "coordinates": [8148, 3689]}, {"type": "Point", "properties": {"PLATE_ID": 611, "NAME": "205770224"}, "coordinates": [8126, 3856]}, {"type": "Point", "properties": {"PLATE_ID": 611, "NAME": "205770227"}, "coordinates": [8122, 3946]}, {"type": "Point", "properties": {"PLATE_ID": 611, "NAME": "205750239"}, "coordinates": [8057, 4255]}, {"type": "Point", "properties": {"PLATE_ID": 611, "NAME": "205770240"}, "coordinates": [8076, 4293]}, {"type": "Point", "properties": {"PLATE_ID": 611, "NAME": "205780226"}, "coordinates": [8135, 3930]}, {"type": "Point", "properties": {"PLATE_ID": 611, "NAME": "205780227"}, "coordinates": [8133, 3948]}, {"type": "Point", "properties": {"PLATE_ID": 611, "NAME": "205780228"}, "coordinates": [8132, 3975]}, {"type": "Point", "properties": {"PLATE_ID": 611, "NAME": "205780229"}, "coordinates": [8128, 4006]}, {"type": "Point", "properties": {"PLATE_ID": 611, "NAME": "205780239"}, "coordinates": [8090, 4270]}, {"type": "Point", "properties": {"PLATE_ID": 611, "NAME": "205780240"}, "coordinates": [8086, 4306]}, {"type": "Point", "properties": {"PLATE_ID": 611, "NAME": "205790226"}, "coordinates": [8147, 3930]}, {"type": "Point", "properties": {"PLATE_ID": 611, "NAME": "205790227"}, "coordinates": [8144, 3951]}, {"type": "Point", "properties": {"PLATE_ID": 611, "NAME": "205770228"}, "coordinates": [8114, 3965]}, {"type": "Point", "properties": {"PLATE_ID": 611, "NAME": "205770229"}, "coordinates": [8115, 3993]}, {"type": "Point", "properties": {"PLATE_ID": 611, "NAME": "205790241"}, "coordinates": [8096, 4330]}, {"type": "Point", "properties": {"PLATE_ID": 611, "NAME": "205790246"}, "coordinates": [8073, 4470]}, {"type": "Point", "properties": {"PLATE_ID": 604, "NAME": "205790250"}, "coordinates": [8183, 5595]}, {"type": "Point", "properties": {"PLATE_ID": 604, "NAME": "205790261"}, "coordinates": [8309, 5785]}, {"type": "Point", "properties": {"PLATE_ID": 611, "NAME": "205800225"}, "coordinates": [8170, 3907]}, {"type": "Point", "properties": {"PLATE_ID": 611, "NAME": "205800226"}, "coordinates": [8158, 3923]}, {"type": "Point", "properties": {"PLATE_ID": 611, "NAME": "205800235"}, "coordinates": [8124, 4166]}, {"type": "Point", "properties": {"PLATE_ID": 611, "NAME": "205800236"}, "coordinates": [8125, 4193]}, {"type": "Point", "properties": {"PLATE_ID": 611, "NAME": "205800238"}, "coordinates": [8117, 4251]}, {"type": "Point", "properties": {"PLATE_ID": 611, "NAME": "205790228"}, "coordinates": [8148, 3977]}, {"type": "Point", "properties": {"PLATE_ID": 611, "NAME": "205790239"}, "coordinates": [8097, 4284]}, {"type": "Point", "properties": {"PLATE_ID": 611, "NAME": "205790240"}, "coordinates": [8095, 4304]}, {"type": "Point", "properties": {"PLATE_ID": 611, "NAME": "205810229"}, "coordinates": [8161, 4019]}, {"type": "Point", "properties": {"PLATE_ID": 611, "NAME": "205810237"}, "coordinates": [8135, 4252]}, {"type": "Point", "properties": {"PLATE_ID": 611, "NAME": "205810238"}, "coordinates": [8135, 4264]}, {"type": "Point", "properties": {"PLATE_ID": 611, "NAME": "205810239"}, "coordinates": [8128, 4284]}, {"type": "Point", "properties": {"PLATE_ID": 611, "NAME": "205810241"}, "coordinates": [8121, 4350]}, {"type": "Point", "properties": {"PLATE_ID": 611, "NAME": "205810242"}, "coordinates": [8116, 4369]}, {"type": "Point", "properties": {"PLATE_ID": 604, "NAME": "205810254"}, "coordinates": [8244, 5636]}, {"type": "Point", "properties": {"PLATE_ID": 611, "NAME": "205820234"}, "coordinates": [8159, 4159]}, {"type": "Point", "properties": {"PLATE_ID": 611, "NAME": "205820235"}, "coordinates": [8158, 4194]}, {"type": "Point", "properties": {"PLATE_ID": 611, "NAME": "205820238"}, "coordinates": [8140, 4272]}, {"type": "Point", "properties": {"PLATE_ID": 611, "NAME": "205800239"}, "coordinates": [8112, 4278]}, {"type": "Point", "properties": {"PLATE_ID": 611, "NAME": "205800240"}, "coordinates": [8112, 4308]}, {"type": "Point", "properties": {"PLATE_ID": 628, "NAME": "205800275"}, "coordinates": [8725, 6835]}, {"type": "Point", "properties": {"PLATE_ID": 604, "NAME": "205820258"}, "coordinates": [8290, 5695]}, {"type": "Point", "properties": {"PLATE_ID": 604, "NAME": "205820259"}, "coordinates": [8300, 5712]}, {"type": "Point", "properties": {"PLATE_ID": 611, "NAME": "205830232"}, "coordinates": [8177, 4128]}, {"type": "Point", "properties": {"PLATE_ID": 611, "NAME": "205830234"}, "coordinates": [8174, 4170]}, {"type": "Point", "properties": {"PLATE_ID": 611, "NAME": "205830235"}, "coordinates": [8166, 4198]}, {"type": "Point", "properties": {"PLATE_ID": 611, "NAME": "205830236"}, "coordinates": [8161, 4215]}, {"type": "Point", "properties": {"PLATE_ID": 611, "NAME": "205830241"}, "coordinates": [8140, 4368]}, {"type": "Point", "properties": {"PLATE_ID": 611, "NAME": "205830243"}, "coordinates": [8136, 4411]}, {"type": "Point", "properties": {"PLATE_ID": 604, "NAME": "205830250"}, "coordinates": [8211, 5529]}, {"type": "Point", "properties": {"PLATE_ID": 611, "NAME": "205820240"}, "coordinates": [8135, 4324]}, {"type": "Point", "properties": {"PLATE_ID": 611, "NAME": "205820241"}, "coordinates": [8131, 4357]}, {"type": "Point", "properties": {"PLATE_ID": 611, "NAME": "205840229"}, "coordinates": [8206, 4046]}, {"type": "Point", "properties": {"PLATE_ID": 611, "NAME": "205840230"}, "coordinates": [8203, 4073]}, {"type": "Point", "properties": {"PLATE_ID": 611, "NAME": "205840231"}, "coordinates": [8200, 4094]}, {"type": "Point", "properties": {"PLATE_ID": 611, "NAME": "205840232"}, "coordinates": [8192, 4136]}, {"type": "Point", "properties": {"PLATE_ID": 611, "NAME": "205840235"}, "coordinates": [8177, 4203]}, {"type": "Point", "properties": {"PLATE_ID": 611, "NAME": "205840236"}, "coordinates": [8176, 4228]}, {"type": "Point", "properties": {"PLATE_ID": 604, "NAME": "205840249"}, "coordinates": [8203, 5489]}, {"type": "Point", "properties": {"PLATE_ID": 604, "NAME": "205840255"}, "coordinates": [8277, 5606]}, {"type": "Point", "properties": {"PLATE_ID": 611, "NAME": "205850228"}, "coordinates": [8215, 4035]}, {"type": "Point", "properties": {"PLATE_ID": 611, "NAME": "205840224"}, "coordinates": [8221, 3896]}, {"type": "Point", "properties": {"PLATE_ID": 611, "NAME": "205840227"}, "coordinates": [8216, 3984]}, {"type": "Point", "properties": {"PLATE_ID": 611, "NAME": "205850232"}, "coordinates": [8205, 4136]}, {"type": "Point", "properties": {"PLATE_ID": 611, "NAME": "205850233"}, "coordinates": [8195, 4144]}, {"type": "Point", "properties": {"PLATE_ID": 611, "NAME": "205850235"}, "coordinates": [8193, 4212]}, {"type": "Point", "properties": {"PLATE_ID": 611, "NAME": "205850236"}, "coordinates": [8182, 4239]}, {"type": "Point", "properties": {"PLATE_ID": 611, "NAME": "205850243"}, "coordinates": [8154, 4424]}, {"type": "Point", "properties": {"PLATE_ID": 604, "NAME": "205850259"}, "coordinates": [8329, 5658]}, {"type": "Point", "properties": {"PLATE_ID": 611, "NAME": "205860231"}, "coordinates": [8216, 4109]}, {"type": "Point", "properties": {"PLATE_ID": 611, "NAME": "205860232"}, "coordinates": [8214, 4131]}, {"type": "Point", "properties": {"PLATE_ID": 611, "NAME": "205860234"}, "coordinates": [8211, 4180]}, {"type": "Point", "properties": {"PLATE_ID": 611, "NAME": "205850229"}, "coordinates": [8213, 4043]}, {"type": "Point", "properties": {"PLATE_ID": 611, "NAME": "205850230"}, "coordinates": [8214, 4086]}, {"type": "Point", "properties": {"PLATE_ID": 611, "NAME": "205850231"}, "coordinates": [8209, 4104]}, {"type": "Point", "properties": {"PLATE_ID": 611, "NAME": "205870230"}, "coordinates": [8236, 4081]}, {"type": "Point", "properties": {"PLATE_ID": 611, "NAME": "205870234"}, "coordinates": [8223, 4193]}, {"type": "Point", "properties": {"PLATE_ID": 611, "NAME": "205870236"}, "coordinates": [8209, 4248]}, {"type": "Point", "properties": {"PLATE_ID": 611, "NAME": "205870239"}, "coordinates": [8203, 4333]}, {"type": "Point", "properties": {"PLATE_ID": 604, "NAME": "205870248"}, "coordinates": [8216, 5433]}, {"type": "Point", "properties": {"PLATE_ID": 628, "NAME": "205870267"}, "coordinates": [8713, 6579]}, {"type": "Point", "properties": {"PLATE_ID": 611, "NAME": "205880228"}, "coordinates": [8255, 4029]}, {"type": "Point", "properties": {"PLATE_ID": 611, "NAME": "205880235"}, "coordinates": [8230, 4239]}, {"type": "Point", "properties": {"PLATE_ID": 611, "NAME": "205880236"}, "coordinates": [8225, 4255]}, {"type": "Point", "properties": {"PLATE_ID": 611, "NAME": "205860235"}, "coordinates": [8204, 4212]}, {"type": "Point", "properties": {"PLATE_ID": 611, "NAME": "205870226"}, "coordinates": [8260, 3976]}, {"type": "Point", "properties": {"PLATE_ID": 611, "NAME": "205870229"}, "coordinates": [8237, 4066]}, {"type": "Point", "properties": {"PLATE_ID": 611, "NAME": "205880241"}, "coordinates": [8207, 4383]}, {"type": "Point", "properties": {"PLATE_ID": 604, "NAME": "205880253"}, "coordinates": [8277, 5492]}, {"type": "Point", "properties": {"PLATE_ID": 801, "NAME": "205890132"}, "coordinates": [7262, 2064]}, {"type": "Point", "properties": {"PLATE_ID": 611, "NAME": "205890230"}, "coordinates": [8258, 4107]}, {"type": "Point", "properties": {"PLATE_ID": 611, "NAME": "205890234"}, "coordinates": [8242, 4215]}, {"type": "Point", "properties": {"PLATE_ID": 611, "NAME": "205890235"}, "coordinates": [8240, 4241]}, {"type": "Point", "properties": {"PLATE_ID": 611, "NAME": "205890236"}, "coordinates": [8241, 4265]}, {"type": "Point", "properties": {"PLATE_ID": 611, "NAME": "205890238"}, "coordinates": [8226, 4308]}, {"type": "Point", "properties": {"PLATE_ID": 611, "NAME": "205890239"}, "coordinates": [8226, 4340]}, {"type": "Point", "properties": {"PLATE_ID": 611, "NAME": "205880238"}, "coordinates": [8212, 4305]}, {"type": "Point", "properties": {"PLATE_ID": 611, "NAME": "205880239"}, "coordinates": [8211, 4332]}, {"type": "Point", "properties": {"PLATE_ID": 611, "NAME": "205880240"}, "coordinates": [8210, 4363]}, {"type": "Point", "properties": {"PLATE_ID": 611, "NAME": "205900236"}, "coordinates": [8249, 4281]}, {"type": "Point", "properties": {"PLATE_ID": 611, "NAME": "205900238"}, "coordinates": [8236, 4316]}, {"type": "Point", "properties": {"PLATE_ID": 611, "NAME": "205900239"}, "coordinates": [8235, 4357]}, {"type": "Point", "properties": {"PLATE_ID": 611, "NAME": "205900240"}, "coordinates": [8228, 4374]}, {"type": "Point", "properties": {"PLATE_ID": 611, "NAME": "205910228"}, "coordinates": [8297, 4076]}, {"type": "Point", "properties": {"PLATE_ID": 611, "NAME": "205910236"}, "coordinates": [8262, 4279]}, {"type": "Point", "properties": {"PLATE_ID": 611, "NAME": "205910237"}, "coordinates": [8260, 4307]}, {"type": "Point", "properties": {"PLATE_ID": 611, "NAME": "205910239"}, "coordinates": [8245, 4358]}, {"type": "Point", "properties": {"PLATE_ID": 611, "NAME": "205920228"}, "coordinates": [8307, 4081]}, {"type": "Point", "properties": {"PLATE_ID": 611, "NAME": "205890240"}, "coordinates": [8223, 4368]}, {"type": "Point", "properties": {"PLATE_ID": 611, "NAME": "205900228"}, "coordinates": [8286, 4062]}, {"type": "Point", "properties": {"PLATE_ID": 611, "NAME": "205930231"}, "coordinates": [8308, 4167]}, {"type": "Point", "properties": {"PLATE_ID": 611, "NAME": "205930238"}, "coordinates": [8281, 4340]}, {"type": "Point", "properties": {"PLATE_ID": 611, "NAME": "205930241"}, "coordinates": [8259, 4426]}, {"type": "Point", "properties": {"PLATE_ID": 628, "NAME": "205930271"}, "coordinates": [8804, 6590]}, {"type": "Point", "properties": {"PLATE_ID": 401, "NAME": "205930281"}, "coordinates": [8052, 8485]}, {"type": "Point", "properties": {"PLATE_ID": 611, "NAME": "205940229"}, "coordinates": [8329, 4119]}, {"type": "Point", "properties": {"PLATE_ID": 611, "NAME": "205940230"}, "coordinates": [8327, 4150]}, {"type": "Point", "properties": {"PLATE_ID": 611, "NAME": "205940232"}, "coordinates": [8317, 4189]}, {"type": "Point", "properties": {"PLATE_ID": 611, "NAME": "205940237"}, "coordinates": [8287, 4341]}, {"type": "Point", "properties": {"PLATE_ID": 611, "NAME": "205920229"}, "coordinates": [8308, 4102]}, {"type": "Point", "properties": {"PLATE_ID": 604, "NAME": "205920260"}, "coordinates": [8381, 5555]}, {"type": "Point", "properties": {"PLATE_ID": 611, "NAME": "205930229"}, "coordinates": [8321, 4120]}, {"type": "Point", "properties": {"PLATE_ID": 604, "NAME": "205940245"}, "coordinates": [8243, 5253]}, {"type": "Point", "properties": {"PLATE_ID": 604, "NAME": "205940248"}, "coordinates": [8278, 5304]}, {"type": "Point", "properties": {"PLATE_ID": 604, "NAME": "205940250"}, "coordinates": [8293, 5338]}, {"type": "Point", "properties": {"PLATE_ID": 611, "NAME": "205950230"}, "coordinates": [8337, 4149]}, {"type": "Point", "properties": {"PLATE_ID": 611, "NAME": "205950231"}, "coordinates": [8333, 4180]}, {"type": "Point", "properties": {"PLATE_ID": 611, "NAME": "205950233"}, "coordinates": [8317, 4231]}, {"type": "Point", "properties": {"PLATE_ID": 611, "NAME": "205950236"}, "coordinates": [8308, 4310]}, {"type": "Point", "properties": {"PLATE_ID": 611, "NAME": "205950241"}, "coordinates": [8285, 4452]}, {"type": "Point", "properties": {"PLATE_ID": 604, "NAME": "205950243"}, "coordinates": [8230, 5184]}, {"type": "Point", "properties": {"PLATE_ID": 801, "NAME": "205960130"}, "coordinates": [7331, 1891]}, {"type": "Point", "properties": {"PLATE_ID": 611, "NAME": "205940238"}, "coordinates": [8291, 4352]}, {"type": "Point", "properties": {"PLATE_ID": 611, "NAME": "205940240"}, "coordinates": [8275, 4402]}, {"type": "Point", "properties": {"PLATE_ID": 611, "NAME": "205940241"}, "coordinates": [8272, 4429]}, {"type": "Point", "properties": {"PLATE_ID": 611, "NAME": "205960241"}, "coordinates": [8297, 4452]}, {"type": "Point", "properties": {"PLATE_ID": 604, "NAME": "205960253"}, "coordinates": [8342, 5372]}, {"type": "Point", "properties": {"PLATE_ID": 604, "NAME": "205960259"}, "coordinates": [8407, 5476]}, {"type": "Point", "properties": {"PLATE_ID": 611, "NAME": "205970237"}, "coordinates": [8324, 4358]}, {"type": "Point", "properties": {"PLATE_ID": 611, "NAME": "205970241"}, "coordinates": [8309, 4469]}, {"type": "Point", "properties": {"PLATE_ID": 604, "NAME": "205970243"}, "coordinates": [8250, 5160]}, {"type": "Point", "properties": {"PLATE_ID": 604, "NAME": "205970244"}, "coordinates": [8257, 5166]}, {"type": "Point", "properties": {"PLATE_ID": 401, "NAME": "205970306"}, "coordinates": [7298, 8851]}, {"type": "Point", "properties": {"PLATE_ID": 611, "NAME": "205980238"}, "coordinates": [8331, 4384]}, {"type": "Point", "properties": {"PLATE_ID": 611, "NAME": "205980241"}, "coordinates": [8321, 4475]}, {"type": "Point", "properties": {"PLATE_ID": 611, "NAME": "205960236"}, "coordinates": [8317, 4309]}, {"type": "Point", "properties": {"PLATE_ID": 604, "NAME": "205990243"}, "coordinates": [8261, 5120]}, {"type": "Point", "properties": {"PLATE_ID": 604, "NAME": "205990248"}, "coordinates": [8311, 5208]}, {"type": "Point", "properties": {"PLATE_ID": 604, "NAME": "205990259"}, "coordinates": [8430, 5442]}, {"type": "Point", "properties": {"PLATE_ID": 611, "NAME": "206000240"}, "coordinates": [8345, 4450]}, {"type": "Point", "properties": {"PLATE_ID": 611, "NAME": "206000241"}, "coordinates": [8339, 4490]}, {"type": "Point", "properties": {"PLATE_ID": 611, "NAME": "206000242"}, "coordinates": [8336, 4499]}, {"type": "Point", "properties": {"PLATE_ID": 604, "NAME": "206000243"}, "coordinates": [8272, 5095]}, {"type": "Point", "properties": {"PLATE_ID": 604, "NAME": "206000244"}, "coordinates": [8282, 5126]}, {"type": "Point", "properties": {"PLATE_ID": 604, "NAME": "206000263"}, "coordinates": [8476, 5485]}, {"type": "Point", "properties": {"PLATE_ID": 611, "NAME": "206010242"}, "coordinates": [8351, 4528]}, {"type": "Point", "properties": {"PLATE_ID": 604, "NAME": "205980244"}, "coordinates": [8260, 5160]}, {"type": "Point", "properties": {"PLATE_ID": 611, "NAME": "205990239"}, "coordinates": [8336, 4431]}, {"type": "Point", "properties": {"PLATE_ID": 611, "NAME": "205990241"}, "coordinates": [8333, 4490]}, {"type": "Point", "properties": {"PLATE_ID": 611, "NAME": "205990242"}, "coordinates": [8327, 4496]}, {"type": "Point", "properties": {"PLATE_ID": 102, "NAME": "203130324"}, "coordinates": [5703, 7208]}, {"type": "Point", "properties": {"PLATE_ID": 302, "NAME": "204370298"}, "coordinates": [6319, 7132]}, {"type": "Point", "properties": {"PLATE_ID": 709, "NAME": "204380169"}, "coordinates": [5720, 2652]}, {"type": "Point", "properties": {"PLATE_ID": 302, "NAME": "204390270"}, "coordinates": [6545, 6426]}, {"type": "Point", "properties": {"PLATE_ID": 503, "NAME": "204400246"}, "coordinates": [6271, 4422]}, {"type": "Point", "properties": {"PLATE_ID": 302, "NAME": "204430308"}, "coordinates": [6288, 7399]}, {"type": "Point", "properties": {"PLATE_ID": 503, "NAME": "204440254"}, "coordinates": [6371, 4570]}, {"type": "Point", "properties": {"PLATE_ID": 302, "NAME": "204440292"}, "coordinates": [6432, 7019]}, {"type": "Point", "properties": {"PLATE_ID": 302, "NAME": "204450292"}, "coordinates": [6443, 7026]}, {"type": "Point", "properties": {"PLATE_ID": 302, "NAME": "204460299"}, "coordinates": [6385, 7216]}, {"type": "Point", "properties": {"PLATE_ID": 503, "NAME": "204470232"}, "coordinates": [6259, 4001]}, {"type": "Point", "properties": {"PLATE_ID": 503, "NAME": "204480232"}, "coordinates": [6259, 3990]}, {"type": "Point", "properties": {"PLATE_ID": 503, "NAME": "204480233"}, "coordinates": [6267, 4022]}, {"type": "Point", "properties": {"PLATE_ID": 702, "NAME": "204490132"}, "coordinates": [5725, 2589]}, {"type": "Point", "properties": {"PLATE_ID": 503, "NAME": "204400256"}, "coordinates": [6346, 4672]}, {"type": "Point", "properties": {"PLATE_ID": 302, "NAME": "204400267"}, "coordinates": [6574, 6363]}, {"type": "Point", "properties": {"PLATE_ID": 302, "NAME": "204400268"}, "coordinates": [6571, 6378]}, {"type": "Point", "properties": {"PLATE_ID": 302, "NAME": "204400298"}, "coordinates": [6347, 7140]}, {"type": "Point", "properties": {"PLATE_ID": 503, "NAME": "204410256"}, "coordinates": [6358, 4662]}, {"type": "Point", "properties": {"PLATE_ID": 302, "NAME": "204410267"}, "coordinates": [6580, 6375]}, {"type": "Point", "properties": {"PLATE_ID": 302, "NAME": "204490297"}, "coordinates": [6432, 7188]}, {"type": "Point", "properties": {"PLATE_ID": 302, "NAME": "204490299"}, "coordinates": [6415, 7232]}, {"type": "Point", "properties": {"PLATE_ID": 702, "NAME": "204500133"}, "coordinates": [5743, 2586]}, {"type": "Point", "properties": {"PLATE_ID": 702, "NAME": "204500134"}, "coordinates": [5770, 2603]}, {"type": "Point", "properties": {"PLATE_ID": 702, "NAME": "204500135"}, "coordinates": [5772, 2627]}, {"type": "Point", "properties": {"PLATE_ID": 702, "NAME": "204500142"}, "coordinates": [5871, 2754]}, {"type": "Point", "properties": {"PLATE_ID": 503, "NAME": "204500220"}, "coordinates": [6202, 3674]}, {"type": "Point", "properties": {"PLATE_ID": 512, "NAME": "204500258"}, "coordinates": [6649, 5262]}, {"type": "Point", "properties": {"PLATE_ID": 512, "NAME": "204500259"}, "coordinates": [6650, 5272]}, {"type": "Point", "properties": {"PLATE_ID": 702, "NAME": "204480132"}, "coordinates": [5712, 2600]}, {"type": "Point", "properties": {"PLATE_ID": 315, "NAME": "203580290"}, "coordinates": [5681, 6580]}, {"type": "Point", "properties": {"PLATE_ID": 106, "NAME": "202150343"}, "coordinates": [5427, 7850]}, {"type": "Point", "properties": {"PLATE_ID": 101, "NAME": "201650257"}, "coordinates": [4463, 5947]}, {"type": "Point", "properties": {"PLATE_ID": 201, "NAME": "202600126"}, "coordinates": [4674, 3069]}, {"type": "Point", "properties": {"PLATE_ID": 201, "NAME": "202080157"}, "coordinates": [4015, 4180]}, {"type": "Point", "properties": {"PLATE_ID": 505, "NAME": "204740246"}, "coordinates": [6937, 4793]}, {"type": "Point", "properties": {"PLATE_ID": 302, "NAME": "204740308"}, "coordinates": [6512, 7611]}, {"type": "Point", "properties": {"PLATE_ID": 302, "NAME": "204740310"}, "coordinates": [6483, 7654]}, {"type": "Point", "properties": {"PLATE_ID": 402, "NAME": "205000256"}, "coordinates": [7412, 6715]}, {"type": "Point", "properties": {"PLATE_ID": 501, "NAME": "205010244"}, "coordinates": [6519, 2932]}, {"type": "Point", "properties": {"PLATE_ID": 402, "NAME": "205010257"}, "coordinates": [7412, 6754]}, {"type": "Point", "properties": {"PLATE_ID": 501, "NAME": "205020242"}, "coordinates": [6491, 2900]}, {"type": "Point", "properties": {"PLATE_ID": 501, "NAME": "205020244"}, "coordinates": [6520, 2919]}, {"type": "Point", "properties": {"PLATE_ID": 501, "NAME": "205020245"}, "coordinates": [6547, 2928]}, {"type": "Point", "properties": {"PLATE_ID": 501, "NAME": "205030242"}, "coordinates": [6491, 2881]}, {"type": "Point", "properties": {"PLATE_ID": 501, "NAME": "205030244"}, "coordinates": [6537, 2886]}, {"type": "Point", "properties": {"PLATE_ID": 501, "NAME": "205030245"}, "coordinates": [6541, 2898]}, {"type": "Point", "properties": {"PLATE_ID": 501, "NAME": "205030246"}, "coordinates": [6551, 2915]}, {"type": "Point", "properties": {"PLATE_ID": 802, "NAME": "204960038"}, "coordinates": [6113, 1849]}, {"type": "Point", "properties": {"PLATE_ID": 402, "NAME": "204990261"}, "coordinates": [7355, 6818]}, {"type": "Point", "properties": {"PLATE_ID": 501, "NAME": "205040246"}, "coordinates": [6558, 2887]}, {"type": "Point", "properties": {"PLATE_ID": 501, "NAME": "205050245"}, "coordinates": [6551, 2858]}, {"type": "Point", "properties": {"PLATE_ID": 501, "NAME": "205050251"}, "coordinates": [6655, 2917]}, {"type": "Point", "properties": {"PLATE_ID": 501, "NAME": "205060245"}, "coordinates": [6561, 2839]}, {"type": "Point", "properties": {"PLATE_ID": 601, "NAME": "205070256"}, "coordinates": [7525, 6947]}, {"type": "Point", "properties": {"PLATE_ID": 601, "NAME": "205080255"}, "coordinates": [7534, 6933]}, {"type": "Point", "properties": {"PLATE_ID": 601, "NAME": "205080256"}, "coordinates": [7532, 6945]}, {"type": "Point", "properties": {"PLATE_ID": 501, "NAME": "205090247"}, "coordinates": [6622, 2784]}, {"type": "Point", "properties": {"PLATE_ID": 501, "NAME": "205090248"}, "coordinates": [6625, 2789]}, {"type": "Point", "properties": {"PLATE_ID": 601, "NAME": "205090255"}, "coordinates": [7546, 6925]}, {"type": "Point", "properties": {"PLATE_ID": 501, "NAME": "205040244"}, "coordinates": [6539, 2875]}, {"type": "Point", "properties": {"PLATE_ID": 501, "NAME": "205040245"}, "coordinates": [6543, 2875]}, {"type": "Point", "properties": {"PLATE_ID": 501, "NAME": "205140245"}, "coordinates": [6617, 2658]}, {"type": "Point", "properties": {"PLATE_ID": 501, "NAME": "205140246"}, "coordinates": [6621, 2671]}, {"type": "Point", "properties": {"PLATE_ID": 501, "NAME": "205160225"}, "coordinates": [6239, 2430]}, {"type": "Point", "properties": {"PLATE_ID": 501, "NAME": "205160244"}, "coordinates": [6597, 2610]}, {"type": "Point", "properties": {"PLATE_ID": 501, "NAME": "205180218"}, "coordinates": [6125, 2318]}, {"type": "Point", "properties": {"PLATE_ID": 501, "NAME": "205180222"}, "coordinates": [6196, 2355]}, {"type": "Point", "properties": {"PLATE_ID": 501, "NAME": "205180243"}, "coordinates": [6598, 2562]}, {"type": "Point", "properties": {"PLATE_ID": 501, "NAME": "205190241"}, "coordinates": [6579, 2501]}, {"type": "Point", "properties": {"PLATE_ID": 402, "NAME": "205190274"}, "coordinates": [7397, 7363]}, {"type": "Point", "properties": {"PLATE_ID": 501, "NAME": "205200241"}, "coordinates": [6576, 2490]}, {"type": "Point", "properties": {"PLATE_ID": 501, "NAME": "205100248"}, "coordinates": [6623, 2784]}, {"type": "Point", "properties": {"PLATE_ID": 501, "NAME": "205110248"}, "coordinates": [6643, 2765]}, {"type": "Point", "properties": {"PLATE_ID": 501, "NAME": "205210227"}, "coordinates": [6317, 2308]}, {"type": "Point", "properties": {"PLATE_ID": 501, "NAME": "205210240"}, "coordinates": [6573, 2455]}, {"type": "Point", "properties": {"PLATE_ID": 501, "NAME": "205210241"}, "coordinates": [6584, 2463]}, {"type": "Point", "properties": {"PLATE_ID": 501, "NAME": "205220226"}, "coordinates": [6303, 2287]}, {"type": "Point", "properties": {"PLATE_ID": 601, "NAME": "205230263"}, "coordinates": [7728, 7180]}, {"type": "Point", "properties": {"PLATE_ID": 402, "NAME": "205230268"}, "coordinates": [7517, 7273]}, {"type": "Point", "properties": {"PLATE_ID": 501, "NAME": "205240228"}, "coordinates": [6357, 2265]}, {"type": "Point", "properties": {"PLATE_ID": 501, "NAME": "205250228"}, "coordinates": [6362, 2230]}, {"type": "Point", "properties": {"PLATE_ID": 501, "NAME": "205250238"}, "coordinates": [6570, 2334]}, {"type": "Point", "properties": {"PLATE_ID": 613, "NAME": "205200247"}, "coordinates": [6790, 2975]}, {"type": "Point", "properties": {"PLATE_ID": 501, "NAME": "205260237"}, "coordinates": [6557, 2304]}, {"type": "Point", "properties": {"PLATE_ID": 501, "NAME": "205260238"}, "coordinates": [6572, 2331]}, {"type": "Point", "properties": {"PLATE_ID": 501, "NAME": "205260239"}, "coordinates": [6581, 2329]}, {"type": "Point", "properties": {"PLATE_ID": 613, "NAME": "205260240"}, "coordinates": [6835, 2743]}, {"type": "Point", "properties": {"PLATE_ID": 501, "NAME": "205270237"}, "coordinates": [6559, 2280]}, {"type": "Point", "properties": {"PLATE_ID": 501, "NAME": "205270239"}, "coordinates": [6592, 2299]}, {"type": "Point", "properties": {"PLATE_ID": 401, "NAME": "205270325"}, "coordinates": [6503, 8277]}, {"type": "Point", "properties": {"PLATE_ID": 501, "NAME": "205280237"}, "coordinates": [6561, 2264]}, {"type": "Point", "properties": {"PLATE_ID": 613, "NAME": "205280239"}, "coordinates": [6856, 2711]}, {"type": "Point", "properties": {"PLATE_ID": 501, "NAME": "205250239"}, "coordinates": [6574, 2343]}, {"type": "Point", "properties": {"PLATE_ID": 501, "NAME": "205260227"}, "coordinates": [6347, 2184]}, {"type": "Point", "properties": {"PLATE_ID": 501, "NAME": "205260236"}, "coordinates": [6537, 2305]}, {"type": "Point", "properties": {"PLATE_ID": 501, "NAME": "205290227"}, "coordinates": [6373, 2131]}, {"type": "Point", "properties": {"PLATE_ID": 501, "NAME": "205300227"}, "coordinates": [6382, 2102]}, {"type": "Point", "properties": {"PLATE_ID": 501, "NAME": "205300236"}, "coordinates": [6550, 2208]}, {"type": "Point", "properties": {"PLATE_ID": 501, "NAME": "205300237"}, "coordinates": [6584, 2215]}, {"type": "Point", "properties": {"PLATE_ID": 402, "NAME": "205300274"}, "coordinates": [7511, 7505]}, {"type": "Point", "properties": {"PLATE_ID": 501, "NAME": "205310227"}, "coordinates": [6390, 2078]}, {"type": "Point", "properties": {"PLATE_ID": 501, "NAME": "205310237"}, "coordinates": [6590, 2189]}, {"type": "Point", "properties": {"PLATE_ID": 402, "NAME": "205310267"}, "coordinates": [7607, 7375]}, {"type": "Point", "properties": {"PLATE_ID": 501, "NAME": "205320227"}, "coordinates": [6396, 2051]}, {"type": "Point", "properties": {"PLATE_ID": 501, "NAME": "205320236"}, "coordinates": [6585, 2169]}, {"type": "Point", "properties": {"PLATE_ID": 613, "NAME": "205280244"}, "coordinates": [6885, 2846]}, {"type": "Point", "properties": {"PLATE_ID": 401, "NAME": "205280319"}, "coordinates": [6664, 8221]}, {"type": "Point", "properties": {"PLATE_ID": 501, "NAME": "205290221"}, "coordinates": [6250, 2071]}, {"type": "Point", "properties": {"PLATE_ID": 401, "NAME": "205320289"}, "coordinates": [7297, 7814]}, {"type": "Point", "properties": {"PLATE_ID": 501, "NAME": "205330228"}, "coordinates": [6426, 2047]}, {"type": "Point", "properties": {"PLATE_ID": 501, "NAME": "205330236"}, "coordinates": [6596, 2130]}, {"type": "Point", "properties": {"PLATE_ID": 612, "NAME": "205330247"}, "coordinates": [7077, 4346]}, {"type": "Point", "properties": {"PLATE_ID": 602, "NAME": "205330250"}, "coordinates": [7785, 6482]}, {"type": "Point", "properties": {"PLATE_ID": 401, "NAME": "205330288"}, "coordinates": [7329, 7807]}, {"type": "Point", "properties": {"PLATE_ID": 501, "NAME": "205340227"}, "coordinates": [6408, 1993]}, {"type": "Point", "properties": {"PLATE_ID": 501, "NAME": "205340236"}, "coordinates": [6607, 2124]}, {"type": "Point", "properties": {"PLATE_ID": 501, "NAME": "205340237"}, "coordinates": [6610, 2133]}, {"type": "Point", "properties": {"PLATE_ID": 501, "NAME": "205320237"}, "coordinates": [6598, 2174]}, {"type": "Point", "properties": {"PLATE_ID": 401, "NAME": "205360313"}, "coordinates": [6835, 8227]}, {"type": "Point", "properties": {"PLATE_ID": 407, "NAME": "205380264"}, "coordinates": [7725, 7394]}, {"type": "Point", "properties": {"PLATE_ID": 407, "NAME": "205380266"}, "coordinates": [7697, 7433]}, {"type": "Point", "properties": {"PLATE_ID": 407, "NAME": "205380267"}, "coordinates": [7676, 7462]}, {"type": "Point", "properties": {"PLATE_ID": 401, "NAME": "205380273"}, "coordinates": [7606, 7578]}, {"type": "Point", "properties": {"PLATE_ID": 501, "NAME": "205390236"}, "coordinates": [6654, 2023]}, {"type": "Point", "properties": {"PLATE_ID": 501, "NAME": "205390237"}, "coordinates": [6672, 2023]}, {"type": "Point", "properties": {"PLATE_ID": 613, "NAME": "205390241"}, "coordinates": [7048, 2695]}, {"type": "Point", "properties": {"PLATE_ID": 401, "NAME": "205390314"}, "coordinates": [6830, 8264]}, {"type": "Point", "properties": {"PLATE_ID": 501, "NAME": "205350229"}, "coordinates": [6455, 2012]}, {"type": "Point", "properties": {"PLATE_ID": 501, "NAME": "205350237"}, "coordinates": [6621, 2113]}, {"type": "Point", "properties": {"PLATE_ID": 613, "NAME": "205360238"}, "coordinates": [6977, 2625]}, {"type": "Point", "properties": {"PLATE_ID": 604, "NAME": "205560259"}, "coordinates": [8137, 6160]}, {"type": "Point", "properties": {"PLATE_ID": 501, "NAME": "205430238"}, "coordinates": [6734, 1960]}, {"type": "Point", "properties": {"PLATE_ID": 612, "NAME": "205440248"}, "coordinates": [7209, 4356]}, {"type": "Point", "properties": {"PLATE_ID": 612, "NAME": "205450248"}, "coordinates": [7219, 4364]}, {"type": "Point", "properties": {"PLATE_ID": 401, "NAME": "205470326"}, "coordinates": [6517, 8438]}, {"type": "Point", "properties": {"PLATE_ID": 602, "NAME": "205490252"}, "coordinates": [7937, 6227]}, {"type": "Point", "properties": {"PLATE_ID": 604, "NAME": "205490259"}, "coordinates": [8087, 6285]}, {"type": "Point", "properties": {"PLATE_ID": 612, "NAME": "205510247"}, "coordinates": [7288, 4336]}, {"type": "Point", "properties": {"PLATE_ID": 604, "NAME": "205510261"}, "coordinates": [8124, 6280]}, {"type": "Point", "properties": {"PLATE_ID": 612, "NAME": "205530246"}, "coordinates": [7317, 4291]}, {"type": "Point", "properties": {"PLATE_ID": 401, "NAME": "205400269"}, "coordinates": [7675, 7529]}, {"type": "Point", "properties": {"PLATE_ID": 612, "NAME": "205420247"}, "coordinates": [7181, 4344]}, {"type": "Point", "properties": {"PLATE_ID": 616, "NAME": "205550217"}, "coordinates": [7567, 3674]}, {"type": "Point", "properties": {"PLATE_ID": 612, "NAME": "205550242"}, "coordinates": [7338, 4189]}, {"type": "Point", "properties": {"PLATE_ID": 616, "NAME": "205560195"}, "coordinates": [7877, 3392]}, {"type": "Point", "properties": {"PLATE_ID": 616, "NAME": "205560218"}, "coordinates": [7561, 3713]}, {"type": "Point", "properties": {"PLATE_ID": 616, "NAME": "205570219"}, "coordinates": [7565, 3738]}, {"type": "Point", "properties": {"PLATE_ID": 612, "NAME": "205570237"}, "coordinates": [7370, 4036]}, {"type": "Point", "properties": {"PLATE_ID": 602, "NAME": "205540254"}, "coordinates": [8008, 6194]}, {"type": "Point", "properties": {"PLATE_ID": 604, "NAME": "205540257"}, "coordinates": [8098, 6181]}, {"type": "Point", "properties": {"PLATE_ID": 604, "NAME": "205540263"}, "coordinates": [8172, 6263]}, {"type": "Point", "properties": {"PLATE_ID": 604, "NAME": "205570255"}, "coordinates": [8088, 6088]}, {"type": "Point", "properties": {"PLATE_ID": 616, "NAME": "205580216"}, "coordinates": [7606, 3695]}, {"type": "Point", "properties": {"PLATE_ID": 616, "NAME": "205580217"}, "coordinates": [7588, 3715]}, {"type": "Point", "properties": {"PLATE_ID": 616, "NAME": "205580227"}, "coordinates": [7461, 3874]}, {"type": "Point", "properties": {"PLATE_ID": 611, "NAME": "205580236"}, "coordinates": [7848, 4109]}, {"type": "Point", "properties": {"PLATE_ID": 611, "NAME": "205580240"}, "coordinates": [7840, 4217]}, {"type": "Point", "properties": {"PLATE_ID": 604, "NAME": "205580254"}, "coordinates": [8091, 6056]}, {"type": "Point", "properties": {"PLATE_ID": 628, "NAME": "205580268"}, "coordinates": [8449, 6941]}, {"type": "Point", "properties": {"PLATE_ID": 401, "NAME": "205580278"}, "coordinates": [7727, 7949]}, {"type": "Point", "properties": {"PLATE_ID": 612, "NAME": "205570239"}, "coordinates": [7366, 4097]}, {"type": "Point", "properties": {"PLATE_ID": 602, "NAME": "205570254"}, "coordinates": [8024, 6143]}, {"type": "Point", "properties": {"PLATE_ID": 616, "NAME": "205590225"}, "coordinates": [7498, 3864]}, {"type": "Point", "properties": {"PLATE_ID": 604, "NAME": "205590257"}, "coordinates": [8128, 6087]}, {"type": "Point", "properties": {"PLATE_ID": 616, "NAME": "205600192"}, "coordinates": [7948, 3451]}, {"type": "Point", "properties": {"PLATE_ID": 616, "NAME": "205600231"}, "coordinates": [7430, 3965]}, {"type": "Point", "properties": {"PLATE_ID": 611, "NAME": "205600232"}, "coordinates": [7877, 3988]}, {"type": "Point", "properties": {"PLATE_ID": 611, "NAME": "205600234"}, "coordinates": [7875, 4052]}, {"type": "Point", "properties": {"PLATE_ID": 602, "NAME": "205600249"}, "coordinates": [7993, 5988]}, {"type": "Point", "properties": {"PLATE_ID": 602, "NAME": "205600251"}, "coordinates": [8023, 6033]}, {"type": "Point", "properties": {"PLATE_ID": 604, "NAME": "205600255"}, "coordinates": [8108, 6030]}, {"type": "Point", "properties": {"PLATE_ID": 616, "NAME": "205590215"}, "coordinates": [7620, 3736]}, {"type": "Point", "properties": {"PLATE_ID": 616, "NAME": "205590217"}, "coordinates": [7600, 3754]}, {"type": "Point", "properties": {"PLATE_ID": 616, "NAME": "205590224"}, "coordinates": [7503, 3848]}, {"type": "Point", "properties": {"PLATE_ID": 615, "NAME": "205610211"}, "coordinates": [7897, 3397]}, {"type": "Point", "properties": {"PLATE_ID": 615, "NAME": "205610213"}, "coordinates": [7882, 3451]}, {"type": "Point", "properties": {"PLATE_ID": 616, "NAME": "205610226"}, "coordinates": [7504, 3925]}, {"type": "Point", "properties": {"PLATE_ID": 611, "NAME": "205610234"}, "coordinates": [7892, 4065]}, {"type": "Point", "properties": {"PLATE_ID": 611, "NAME": "205610235"}, "coordinates": [7887, 4088]}, {"type": "Point", "properties": {"PLATE_ID": 611, "NAME": "205610237"}, "coordinates": [7887, 4146]}, {"type": "Point", "properties": {"PLATE_ID": 615, "NAME": "205620212"}, "coordinates": [7896, 3426]}, {"type": "Point", "properties": {"PLATE_ID": 602, "NAME": "205620247"}, "coordinates": [7992, 5932]}, {"type": "Point", "properties": {"PLATE_ID": 401, "NAME": "205620308"}, "coordinates": [7089, 8448]}, {"type": "Point", "properties": {"PLATE_ID": 604, "NAME": "205600256"}, "coordinates": [8117, 6046]}, {"type": "Point", "properties": {"PLATE_ID": 401, "NAME": "205600308"}, "coordinates": [7084, 8417]}, {"type": "Point", "properties": {"PLATE_ID": 616, "NAME": "205610191"}, "coordinates": [7975, 3447]}, {"type": "Point", "properties": {"PLATE_ID": 602, "NAME": "205630250"}, "coordinates": [8034, 5963]}, {"type": "Point", "properties": {"PLATE_ID": 401, "NAME": "205630274"}, "coordinates": [7844, 7952]}, {"type": "Point", "properties": {"PLATE_ID": 401, "NAME": "205630308"}, "coordinates": [7093, 8460]}, {"type": "Point", "properties": {"PLATE_ID": 619, "NAME": "205640190"}, "coordinates": [7984, 3511]}, {"type": "Point", "properties": {"PLATE_ID": 616, "NAME": "205640222"}, "coordinates": [7574, 3924]}, {"type": "Point", "properties": {"PLATE_ID": 611, "NAME": "205640235"}, "coordinates": [7924, 4108]}, {"type": "Point", "properties": {"PLATE_ID": 604, "NAME": "205640257"}, "coordinates": [8155, 5983]}, {"type": "Point", "properties": {"PLATE_ID": 628, "NAME": "205640266"}, "coordinates": [8482, 6829]}, {"type": "Point", "properties": {"PLATE_ID": 619, "NAME": "205650187"}, "coordinates": [8030, 3495]}, {"type": "Point", "properties": {"PLATE_ID": 615, "NAME": "205660225"}, "coordinates": [7876, 3799]}, {"type": "Point", "properties": {"PLATE_ID": 615, "NAME": "205630205"}, "coordinates": [7958, 3256]}, {"type": "Point", "properties": {"PLATE_ID": 602, "NAME": "205630249"}, "coordinates": [8021, 5952]}, {"type": "Point", "properties": {"PLATE_ID": 615, "NAME": "205630215"}, "coordinates": [7901, 3509]}, {"type": "Point", "properties": {"PLATE_ID": 619, "NAME": "205670183"}, "coordinates": [8099, 3516]}, {"type": "Point", "properties": {"PLATE_ID": 615, "NAME": "205670222"}, "coordinates": [7910, 3738]}, {"type": "Point", "properties": {"PLATE_ID": 611, "NAME": "205670231"}, "coordinates": [7974, 3990]}, {"type": "Point", "properties": {"PLATE_ID": 611, "NAME": "205670239"}, "coordinates": [7952, 4212]}, {"type": "Point", "properties": {"PLATE_ID": 611, "NAME": "205670246"}, "coordinates": [7941, 4414]}, {"type": "Point", "properties": {"PLATE_ID": 611, "NAME": "205680231"}, "coordinates": [7991, 4009]}, {"type": "Point", "properties": {"PLATE_ID": 611, "NAME": "205680232"}, "coordinates": [7980, 4025]}, {"type": "Point", "properties": {"PLATE_ID": 611, "NAME": "205680233"}, "coordinates": [7982, 4069]}, {"type": "Point", "properties": {"PLATE_ID": 611, "NAME": "205680242"}, "coordinates": [7958, 4315]}, {"type": "Point", "properties": {"PLATE_ID": 611, "NAME": "205660229"}, "coordinates": [7965, 3946]}, {"type": "Point", "properties": {"PLATE_ID": 611, "NAME": "205690230"}, "coordinates": [8004, 3981]}, {"type": "Point", "properties": {"PLATE_ID": 611, "NAME": "205690231"}, "coordinates": [7999, 4009]}, {"type": "Point", "properties": {"PLATE_ID": 611, "NAME": "205690233"}, "coordinates": [7995, 4062]}, {"type": "Point", "properties": {"PLATE_ID": 611, "NAME": "205700229"}, "coordinates": [8017, 3964]}, {"type": "Point", "properties": {"PLATE_ID": 611, "NAME": "205700230"}, "coordinates": [8012, 3982]}, {"type": "Point", "properties": {"PLATE_ID": 611, "NAME": "205700231"}, "coordinates": [8016, 4023]}, {"type": "Point", "properties": {"PLATE_ID": 611, "NAME": "205700232"}, "coordinates": [8011, 4034]}, {"type": "Point", "properties": {"PLATE_ID": 611, "NAME": "205700233"}, "coordinates": [8009, 4069]}, {"type": "Point", "properties": {"PLATE_ID": 611, "NAME": "205700234"}, "coordinates": [8003, 4091]}, {"type": "Point", "properties": {"PLATE_ID": 611, "NAME": "205700236"}, "coordinates": [7996, 4144]}, {"type": "Point", "properties": {"PLATE_ID": 611, "NAME": "205680243"}, "coordinates": [7960, 4329]}, {"type": "Point", "properties": {"PLATE_ID": 401, "NAME": "205680322"}, "coordinates": [6673, 8604]}, {"type": "Point", "properties": {"PLATE_ID": 611, "NAME": "205690229"}, "coordinates": [8006, 3955]}, {"type": "Point", "properties": {"PLATE_ID": 611, "NAME": "205710227"}, "coordinates": [8043, 3904]}, {"type": "Point", "properties": {"PLATE_ID": 611, "NAME": "205710230"}, "coordinates": [8028, 4000]}, {"type": "Point", "properties": {"PLATE_ID": 611, "NAME": "205710231"}, "coordinates": [8023, 4024]}, {"type": "Point", "properties": {"PLATE_ID": 611, "NAME": "205710232"}, "coordinates": [8027, 4052]}, {"type": "Point", "properties": {"PLATE_ID": 611, "NAME": "205710233"}, "coordinates": [8021, 4066]}, {"type": "Point", "properties": {"PLATE_ID": 611, "NAME": "205710234"}, "coordinates": [8017, 4095]}, {"type": "Point", "properties": {"PLATE_ID": 611, "NAME": "205710243"}, "coordinates": [7995, 4354]}, {"type": "Point", "properties": {"PLATE_ID": 611, "NAME": "205710244"}, "coordinates": [7989, 4379]}, {"type": "Point", "properties": {"PLATE_ID": 611, "NAME": "205710245"}, "coordinates": [7991, 4400]}, {"type": "Point", "properties": {"PLATE_ID": 604, "NAME": "205710257"}, "coordinates": [8208, 5869]}, {"type": "Point", "properties": {"PLATE_ID": 611, "NAME": "205700244"}, "coordinates": [7979, 4369]}, {"type": "Point", "properties": {"PLATE_ID": 628, "NAME": "205700267"}, "coordinates": [8548, 6760]}, {"type": "Point", "properties": {"PLATE_ID": 611, "NAME": "205710226"}, "coordinates": [8044, 3889]}, {"type": "Point", "properties": {"PLATE_ID": 101, "NAME": "201480258"}, "coordinates": [4285, 6118]}, {"type": "Point", "properties": {"PLATE_ID": 101, "NAME": "201640262"}, "coordinates": [4474, 6097]}, {"type": "Point", "properties": {"PLATE_ID": 101, "NAME": "201250292"}, "coordinates": [4323, 7157]}, {"type": "Point", "properties": {"PLATE_ID": 101, "NAME": "201980260"}, "coordinates": [4835, 5825]}, {"type": "Point", "properties": {"PLATE_ID": 128, "NAME": "200940292"}, "coordinates": [3318, 7889]}]}}, "type": "Topology", "transform": {"translate": [-179.091233, -89.14086], "scale": [0.035328391039103915, 0.017861348234823483]}, "arcs": []}